<metadata><idinfo><citation><citeinfo><origin>U.S. Department of Commerce, U.S. Census Bureau, Geography Division</origin><pubdate>2010</pubdate><title>Nebraska Zip Codes - TIGER 2010</title><edition>2010</edition><geoform>vector digital data</geoform><onlink>http://www.census.gov/geo/www/tiger</onlink></citeinfo></citation><descript><abstract>The TIGER/Line Files are shapefiles and related database files (.dbf) that are an extract of selected geographic and cartographic information from the U.S. Census Bureau's Master Address File / Topologically Integrated Geographic Encoding and Referencing (MAF/TIGER) Database (MTDB). The MTDB represents a seamless national file with no overlaps or gaps between parts, however, each TIGER/Line File is designed to stand alone as an independent data set, or they can be combined to cover the entire nation. ZIP Code Tabulation Areas (ZCTAs) are approximate area representations of U.S. Postal Service (USPS) ZIP Code service areas that the Census Bureau creates to present statistical data from Census 2000. The Census Bureau creates ZCTAs for the United States, Puerto Rico, American Samoa, Guam, the Commonwealth of the Northern Mariana Islands, and the U.S. Virgin Islands for the 2010 Census. Data users should not use ZCTAs to identify the official USPS ZIP Code for mail delivery. The USPS makes periodic changes to ZIP Codes to support more efficient mail delivery. For the 2010 Census, ZCTAs should more accurately represent the actual ZIP Codes at the time of their delineation than they did for Census 2000. This is because that before the tabulation blocks, which the ZCTAs are built from, were delineated for the 2010 Census, the Census Bureau undertook the process of inserting lines that could be used as 2010 Census tabulation block boundaries, and these lines split polygons where the result would be that a significant number of addresses would occur on either one or both sides of the line associated with a single ZIP Code. Each 2010 Census tabulation block that contains addresses is assigned to a single ZCTA, usually to the ZCTA that reflects the most frequently occurring ZIP Code for the addresses within that tabulation block. As a result, ZIP Codes associated with address ranges found in the Address Ranges relationship file may not always match the ZCTA. Blocks that do not contain addresses but are completely surrounded by a single ZCTA (enclaves) are assigned to the surrounding ZCTA. A ZCTA may not exist for every USPS ZIP Code. Some ZIP Codes may not have a matching ZCTA because too few addresses were associated with the specific ZIP Code or the ZIP Code was not the most frequently occurring ZIP Code within any of the blocks were it exists. The Census Bureau uses the addresses stored within MTDB to delineate ZCTAs, and at the time of the 2010 Census the MTDB primarily included addresses for residential or at least potentially residential structures, so ZCTAs representing only non-residential structures are infrequent. Also, in each tabulation block, if a choice existed between using a potential city-style mail delivery ZIP Code for an address or a post office box ZIP Code, the city-style mail delivery ZIP Code was preferred for the 2010 Census ZCTA delineation. The Census Bureau identifies 5-digit ZCTAs using a five-character numeric code that represents the most frequently occurring USPS ZIP Code within that ZCTA, and this code may contain leading zeros.</abstract><purpose>In order for others to use the information in the Census MAF/TIGER database in a geographic information system (GIS) or for other geographic applications, the Census Bureau releases to the public extracts of the database in the form of TIGER/Line Shapefiles.</purpose><Subject_Entity>Nebraska(31)</Subject_Entity></descript><timeperd><timeinfo><rngdates><begdate>201001</begdate><enddate>201007</enddate></rngdates></timeinfo><current>Publication Date</current></timeperd><status><progress>Complete</progress><update>TIGER/Line Shapefiles are extracted from the Census MAF/TIGER database.  No changes or updates will be made to this version of the TIGER/Line Shapefiles.  Future releases of TIGER/Line Shapefiles will reflect updates made to the Census MAF/TIGER database.</update></status><spdom><bounding><westbc>-104.053514</westbc><eastbc>-95.30829</eastbc><northbc>43.001707</northbc><southbc>39.999932</southbc></bounding></spdom><keywords><place><placekt>INCITS.38-200x (R2004),INCITS.31-200x (R2007),INCITS.454-200x,INCITS 455-200x,INCITS 446-2008</placekt><placekey>United States</placekey><placekey>U.S.</placekey><placekey>State or Equivalent Entity</placekey><placekey>Nebraska</placekey><placekey>NE</placekey><placekey>31</placekey></place><theme><themekey>ZIP Code Tabulation Area</themekey><themekey>ZCTA</themekey><themekey>Polygon</themekey><themekey>State or equivalent entity</themekey><themekey>Zip Code</themekey><themekey>boundaries</themekey></theme></keywords><accconst>None</accconst><useconst>The TIGER/Line Shapefile products are not copyrighted however TIGER/Line and Census TIGER are registered trademarks of the U.S. Census Bureau.  These products are free to use in a product or publication, however acknowledgement must be given to the U.S. Census Bureau as the source.
The boundary information in the TIGER/Line Shapefiles are for statistical data collection and tabulation purposes only; their depiction and designation for statistical purposes does not constitute a determination of jurisdictional authority or rights of ownership or entitlement and they are not legal land descriptions.Coordinates in the TIGER/Line shapefiles have six implied decimal places, but the positional accuracy of these coordinates is not as great as the six decimal places suggest.</useconst><Title_13_Restrictions>Yes, the data are free from Title 13 restrictions</Title_13_Restrictions><ptcontac><cntinfo><cntorgp><cntorg>U.S. Department of Commerce, U.S. Census Bureau, Geography Division, Geographic Products Branch</cntorg></cntorgp><cntaddr><addrtype>Mailing address</addrtype><address>4600 Silver Hill Road, Stop 7400</address><city>Washington</city><state>DC</state><postal>20233-7400</postal><country>United States</country></cntaddr><cntvoice>301-763-1128</cntvoice><cntfax>301-763-4710</cntfax><cntemail>geo.tiger@census.gov</cntemail></cntinfo></ptcontac></idinfo><Data_Set_Character_Set>8859part1</Data_Set_Character_Set><Data_Set_Language>eng</Data_Set_Language><dataqual><attracc><attraccr>Accurate against Federal Information Processing Standards (FIPS), FIPS Publication 6-4, and FIPS-55 at the 100% level for the codes and base names.  The remaining attribute information has been examined but has not been fully tested for accuracy.</attraccr></attracc><logic>The Census Bureau performed automated tests to ensure logical consistency and limits of shapefiles.  Segments making up the outer and inner boundaries of a polygon tie end-to-end to completely enclose the area.  All polygons are tested for closure.
The Census Bureau uses its internally developed geographic update system to enhance and modify spatial and attribute data in the Census MAF/TIGER database.  Standard geographic codes, such as FIPS codes for states, counties, municipalities, county subdivisions, places, American Indian/Alaska Native/Native Hawaiian areas, and congressional districts are used when encoding spatial entities.  The Census Bureau performed spatial data tests for logical consistency of the codes during the compilation of the original Census MAF/TIGER database files.  Most of the codes for geographic entities except states, counties, urban areas, Core Based Statistical Areas (CBSAs), American Indian Areas (AIAs), and congressional districts were provided to the Census Bureau by the USGS, the agency responsible for maintaining FIPS 55.  Feature attribute information has been examined but has not been fully tested for consistency.
For the TIGER/Line Shapefiles, the Point and Vector Object Count for the G-polygon SDTS Point and Vector Object Type reflects the number of records in the shapefile attribute table.  For multi-polygon features, only one attribute record exists for each multi-polygon rather than one attribute record per individual G-polygon component of the multi-polygon feature.  TIGER/Line Shapefile multi-polygons are an exception to the G-polygon object type classification.  Therefore, when multi-polygons exist in a shapefile, the object count will be less than the actual number of G-polygons.</logic><complete>Data completeness of the TIGER/Line Shapefiles reflects the contents of the Census MAF/TIGER database at the time the TIGER/Line Shapefiles were created.</complete><lineage><srcinfo><srccite><citeinfo><origin>U.S. Department of Commerce, U.S. Census Bureau, Geography Division</origin><pubdate>Unpublished material</pubdate><title>Census MAF/TIGER database</title></citeinfo></srccite><typesrc>online</typesrc><srctime><timeinfo><rngdates><begdate>201001</begdate><enddate>201007</enddate></rngdates></timeinfo><srccurr>Publication Date</srccurr></srctime><srccitea>MAF/TIGER</srccitea><srccontr>The selected geographic and cartographic information (line segments) are derived from the U.S. Census Bureau's Master Address File Topologically Integrated Geographic Encoding and Referencing (MAF/TIGER) database.</srccontr></srcinfo><procstep><procdesc>TIGER/Line Shapefiles are extracted from the Census MAF/TIGER database by nation, state, county, and entity.  Census MAF/TIGER data for all of the aforementioned geographic entities are then distributed among the shapefiles each containing attributes for line, polygon, or landmark geographic data. </procdesc><srcused>Census MAF/TIGER</srcused><procdate>2010</procdate></procstep></lineage></dataqual><spdoinfo><indspref>Federal Information Processing Standards (FIPS), ANSI, and feature names.</indspref><direct>Vector</direct><ptvctinf><esriterm><efeatyp Sync="TRUE">Simple</efeatyp><efeageom code="4" Sync="TRUE"></efeageom><esritopo Sync="TRUE">FALSE</esritopo><efeacnt Sync="TRUE">0</efeacnt><spindex Sync="TRUE">FALSE</spindex><linrefer Sync="TRUE">FALSE</linrefer></esriterm></ptvctinf></spdoinfo><spref><horizsys><geodetic><horizdn>North American Datum of 1983 in the 48 contiguous states, the District of Columbia, Alaska, Hawaii, Puerto Rico, the Virgin Islands of the United States, and the Pacific Island Areas.</horizdn><ellips>Geodetic Reference System 80</ellips><semiaxis>6378137</semiaxis><denflat>298257</denflat></geodetic></horizsys></spref><eainfo><detailed Name="ZipCodesSP"><enttyp><enttypl Sync="TRUE">ZipCodesSP</enttypl><enttypd>2010 Census 5-digit ZIP Code Tabulation Area (ZCTA5) State-based</enttypd><enttypds>U.S. Census Bureau</enttypds><enttypt Sync="TRUE">Feature Class</enttypt><enttypc Sync="TRUE">0</enttypc></enttyp><attr><attrlabl Sync="TRUE">FID</attrlabl><attalias Sync="TRUE">FID</attalias><attrtype Sync="TRUE">OID</attrtype><attwidth Sync="TRUE">4</attwidth><atprecis Sync="TRUE">0</atprecis><attscale Sync="TRUE">0</attscale><attrdef Sync="TRUE">Internal feature number.</attrdef><attrdefs Sync="TRUE">ESRI</attrdefs><attrdomv><udom Sync="TRUE">Sequential unique whole numbers that are automatically generated.</udom></attrdomv></attr><attr><attrlabl Sync="TRUE">Shape</attrlabl><attalias Sync="TRUE">Shape</attalias><attrtype Sync="TRUE">Geometry</attrtype><attwidth Sync="TRUE">0</attwidth><atprecis Sync="TRUE">0</atprecis><attscale Sync="TRUE">0</attscale><attrdef Sync="TRUE">Feature geometry.</attrdef><attrdefs Sync="TRUE">ESRI</attrdefs><attrdomv><udom Sync="TRUE">Coordinates defining the features.</udom></attrdomv></attr><attr><attrlabl>STATEFP10</attrlabl><attrdef>2010 Census state Federal Information Processing Standards
                 (FIPS) code</attrdef><attrdefs>U.S. Census Bureau</attrdefs><attrdomv><codesetd><codesetn>INCITS.38-200x (R2004), Codes for the Identification of
                      the States, the District of Columbia, Puerto Rico, and the
                      Insular Areas of the United States (Formerly FIPS 5-2)</codesetn><codesets>U.S. Census Bureau</codesets></codesetd></attrdomv><attalias Sync="TRUE">STATEFP10</attalias><attrtype Sync="TRUE">String</attrtype><attwidth Sync="TRUE">2</attwidth><atprecis Sync="TRUE">0</atprecis><attscale Sync="TRUE">0</attscale></attr><attr><attrlabl>ZCTA5CE10</attrlabl><attrdef>2010 Census 5-digit ZIP Code Tabulation Area code</attrdef><attrdefs>U.S. Census Bureau</attrdefs><attrdomv><edom><edomv>00401 to 99950</edomv><edomvd>Five-digit ZIP code</edomvd><edomvds>U.S. Census Bureau</edomvds></edom></attrdomv><attalias Sync="TRUE">ZCTA5CE10</attalias><attrtype Sync="TRUE">String</attrtype><attwidth Sync="TRUE">5</attwidth><atprecis Sync="TRUE">0</atprecis><attscale Sync="TRUE">0</attscale></attr><attr><attrlabl>GEOID10</attrlabl><attrdef>2010 Census 5-digit ZIP Code Tabulation Area identifier, 2010
                 Census 5-digit ZIP Code Tabulation Area code</attrdef><attrdefs>U.S. Census Bureau</attrdefs><attrdomv><udom>2010 Census 5-digit ZIP Code Tabulation Area code found in
                ZCTA5CE10</udom></attrdomv><attalias Sync="TRUE">GEOID10</attalias><attrtype Sync="TRUE">String</attrtype><attwidth Sync="TRUE">7</attwidth><atprecis Sync="TRUE">0</atprecis><attscale Sync="TRUE">0</attscale></attr><attr><attrlabl>CLASSFP10</attrlabl><attrdef>2010 Census Federal Information Processing Standards (FIPS) 55
                 class code</attrdef><attrdefs>U.S. Census Bureau</attrdefs><attrdomv><edom><edomv>B5</edomv><edomvd>Five-digit ZCTA</edomvd><edomvds>U.S. Census Bureau</edomvds></edom></attrdomv><attalias Sync="TRUE">CLASSFP10</attalias><attrtype Sync="TRUE">String</attrtype><attwidth Sync="TRUE">2</attwidth><atprecis Sync="TRUE">0</atprecis><attscale Sync="TRUE">0</attscale></attr><attr><attrlabl>MTFCC10</attrlabl><attrdef>MAF/TIGER feature class code</attrdef><attrdefs>U.S. Census Bureau</attrdefs><attrdomv><edom><edomv>G6350</edomv><edomvd>ZIP Code Tabulation Area (5-digit)</edomvd><edomvds>U.S. Census Bureau</edomvds></edom></attrdomv><attalias Sync="TRUE">MTFCC10</attalias><attrtype Sync="TRUE">String</attrtype><attwidth Sync="TRUE">5</attwidth><atprecis Sync="TRUE">0</atprecis><attscale Sync="TRUE">0</attscale></attr><attr><attrlabl>FUNCSTAT10</attrlabl><attrdef>2010 Census functional status</attrdef><attrdefs>U.S. Census Bureau</attrdefs><attrdomv><edom><edomv>S</edomv><edomvd>Statistical entity</edomvd><edomvds>U.S. Census Bureau</edomvds></edom></attrdomv><attalias Sync="TRUE">FUNCSTAT10</attalias><attrtype Sync="TRUE">String</attrtype><attwidth Sync="TRUE">1</attwidth><atprecis Sync="TRUE">0</atprecis><attscale Sync="TRUE">0</attscale></attr><attr><attrlabl>ALAND10</attrlabl><attrdef>2010 Census land area (square meters)</attrdef><attrdefs>U.S. Census Bureau</attrdefs><attrdomv><edom><edomv>0 to 9,999,999,999,999</edomv><edomvd>Blank</edomvd><edomvds>U.S. Census Bureau</edomvds></edom></attrdomv><attalias Sync="TRUE">ALAND10</attalias><attrtype Sync="TRUE">Double</attrtype><attwidth Sync="TRUE">14</attwidth><atprecis Sync="TRUE">14</atprecis><attscale Sync="TRUE">0</attscale></attr><attr><attrlabl>AWATER10</attrlabl><attrdef>2010 Census water area (square meters)</attrdef><attrdefs>U.S. Census Bureau</attrdefs><attrdomv><edom><edomv>0 to 9,999,999,999,999</edomv><edomvd>Blank</edomvd><edomvds>U.S. Census Bureau</edomvds></edom></attrdomv><attalias Sync="TRUE">AWATER10</attalias><attrtype Sync="TRUE">Double</attrtype><attwidth Sync="TRUE">14</attwidth><atprecis Sync="TRUE">14</atprecis><attscale Sync="TRUE">0</attscale></attr><attr><attrlabl>INTPTLAT10</attrlabl><attrdef>2010 Census latitude of the internal point</attrdef><attrdefs>U.S. Census Bureau</attrdefs><attrdomv><edom><edomv>00</edomv><edomvd>Blank</edomvd><edomvds>U.S. Census Bureau</edomvds></edom></attrdomv><attalias Sync="TRUE">INTPTLAT10</attalias><attrtype Sync="TRUE">String</attrtype><attwidth Sync="TRUE">11</attwidth><atprecis Sync="TRUE">0</atprecis><attscale Sync="TRUE">0</attscale></attr><attr><attrlabl>INTPTLON10</attrlabl><attrdef>2010 Census longitude of the internal point</attrdef><attrdefs>U.S. Census Bureau</attrdefs><attrdomv><edom><edomv>00</edomv><edomvd>Blank</edomvd><edomvds>U.S. Census Bureau</edomvds></edom></attrdomv><attalias Sync="TRUE">INTPTLON10</attalias><attrtype Sync="TRUE">String</attrtype><attwidth Sync="TRUE">12</attwidth><atprecis Sync="TRUE">0</atprecis><attscale Sync="TRUE">0</attscale></attr><attr><attrlabl>PARTFLG10</attrlabl><attrdef>Part flag identifying if all or part of the 2010 Census entity
                 is within the file</attrdef><attrdefs>U.S. Census Bureau</attrdefs><attrdomv><edom><edomv>00</edomv><edomvd>Blank</edomvd><edomvds>U.S. Census Bureau</edomvds></edom></attrdomv><attalias Sync="TRUE">PARTFLG10</attalias><attrtype Sync="TRUE">String</attrtype><attwidth Sync="TRUE">1</attwidth><atprecis Sync="TRUE">0</atprecis><attscale Sync="TRUE">0</attscale></attr><attr><attrlabl Sync="TRUE">Shape_area</attrlabl><attalias Sync="TRUE">Shape_area</attalias><attrtype Sync="TRUE">Double</attrtype><attwidth Sync="TRUE">19</attwidth><atprecis Sync="TRUE">0</atprecis><attscale Sync="TRUE">0</attscale><attrdef Sync="TRUE">Area of feature in internal units squared.</attrdef><attrdefs Sync="TRUE">ESRI</attrdefs><attrdomv><udom Sync="TRUE">Positive real numbers that are automatically generated.</udom></attrdomv></attr><attr><attrlabl Sync="TRUE">Shape_len</attrlabl><attalias Sync="TRUE">Shape_len</attalias><attrtype Sync="TRUE">Double</attrtype><attwidth Sync="TRUE">19</attwidth><atprecis Sync="TRUE">0</atprecis><attscale Sync="TRUE">0</attscale></attr></detailed></eainfo><distinfo><distrib><cntinfo><cntorgp><cntorg>U.S. Department of Commerce, U.S. Census Bureau, Geography Division, Geographic Products Branch</cntorg></cntorgp><cntaddr><addrtype>Mailing address</addrtype><address>4600 Silver Hill Road, Stop 7400</address><city>Washington</city><state>DC</state><postal>20233-7400</postal><country>United States</country></cntaddr><cntvoice>301-763-1128</cntvoice><cntfax>301-763-4710</cntfax><cntemail>geo.tiger@census.gov</cntemail></cntinfo></distrib><distliab>No warranty, expressed or implied is made with regard to the accuracy of these data, and no liability is assumed by the U.S. Government in general or the U.S. Census Bureau in specific as to the spatial or attribute accuracy of the data.  The act of distribution shall not constitute any such warranty and no responsibility is assumed by the U.S. government in the use of these files.  The boundary information in the TIGER/Line Shapefiles is for statistical data collection and tabulation purposes only; their depiction and designation for statistical purposes do not constitute a determination of jurisdictional authority or rights of ownership or entitlement and they are not legal land descriptions.</distliab><stdorder><digform><digtinfo><formname>TGRSHP (compressed)</formname><filedec>PK-ZIP, version 1.93 A or higher</filedec></digtinfo><digtopt><onlinopt><computer><networka><networkr>http://www.census.gov/geo/www/tiger</networkr></networka></computer></onlinopt><offoptn><offmedia>DVD-ROM (Only if offered offline)</offmedia><recfmt>ISO 9660</recfmt></offoptn></digtopt></digform><fees>The online copy of the TIGER/Line files may be accessed without charge.</fees><ordering>To obtain more information about ordering TIGER/Line shapefiles visit http://www.census.gov/geo/www/tiger </ordering></stdorder><techpreq>The TIGER/Line shapefiles contain geographic data only and do not include display mapping software or statistical data.  For information on how to use the TIGER/Line shapefile data with specific software package users shall contact the company that produced the software.</techpreq></distinfo><metainfo><metd>20100507</metd><metc><cntinfo><cntorgp><cntorg>U.S. Department of Commerce, U.S. Census Bureau, Geography Division, Geographic Products Branch</cntorg></cntorgp><cntaddr><addrtype>Mailing address</addrtype><address>4600 Silver Hill Road, Stop 7400</address><city>Washington</city><state>DC</state><postal>20233-7400</postal><country>United States</country></cntaddr><cntvoice>301-763-1128</cntvoice><cntfax>301-763-4710</cntfax><cntemail>geo.tiger@census.gov</cntemail></cntinfo></metc><metstdn>FGDC Content Standards for Digital Geospatial Metadata</metstdn><metstdv>FGDC-STD-001-1998</metstdv><Metadata_Character_Set>8859part1</Metadata_Character_Set><Metadata_File_Identifier>tl_2010_31_zcta510.shp.xml</Metadata_File_Identifier><Metadata_Language>eng</Metadata_Language></metainfo><Esri><DataProperties><itemProps><itemName Sync="TRUE">ZipCodesSP</itemName><nativeExtBox><westBL Sync="TRUE">522356.397204</westBL><eastBL Sync="TRUE">2954215.292335</eastBL><southBL Sync="TRUE">61268.399692</southBL><northBL Sync="TRUE">1179233.516776</northBL><exTypeCode Sync="TRUE">1</exTypeCode></nativeExtBox><itemSize Sync="TRUE">0.000</itemSize><itemLocation><linkage Sync="TRUE">file://\\PC29060\doq5\UTM\ZipCodesSP\ZipCodesSP.shp</linkage><protocol Sync="TRUE">Local Area Network</protocol></itemLocation><imsContentType Sync="TRUE">002</imsContentType></itemProps><coordRef><type Sync="TRUE">Projected</type><geogcsn Sync="TRUE">GCS_North_American_1983</geogcsn><csUnits Sync="TRUE">Linear Unit: Foot_US (0.304801)</csUnits><peXml Sync="TRUE">&lt;ProjectedCoordinateSystem xsi:type='typens:ProjectedCoordinateSystem' xmlns:xsi='http://www.w3.org/2001/XMLSchema-instance' xmlns:xs='http://www.w3.org/2001/XMLSchema' xmlns:typens='http://www.esri.com/schemas/ArcGIS/10.0'&gt;&lt;WKT&gt;PROJCS[&amp;quot;NAD_1983_StatePlane_Nebraska_FIPS_2600_Feet&amp;quot;,GEOGCS[&amp;quot;GCS_North_American_1983&amp;quot;,DATUM[&amp;quot;D_North_American_1983&amp;quot;,SPHEROID[&amp;quot;GRS_1980&amp;quot;,6378137.0,298.257222101]],PRIMEM[&amp;quot;Greenwich&amp;quot;,0.0],UNIT[&amp;quot;Degree&amp;quot;,0.0174532925199433]],PROJECTION[&amp;quot;Lambert_Conformal_Conic&amp;quot;],PARAMETER[&amp;quot;False_Easting&amp;quot;,1640416.666666667],PARAMETER[&amp;quot;False_Northing&amp;quot;,0.0],PARAMETER[&amp;quot;Central_Meridian&amp;quot;,-100.0],PARAMETER[&amp;quot;Standard_Parallel_1&amp;quot;,40.0],PARAMETER[&amp;quot;Standard_Parallel_2&amp;quot;,43.0],PARAMETER[&amp;quot;Latitude_Of_Origin&amp;quot;,39.83333333333334],UNIT[&amp;quot;Foot_US&amp;quot;,0.3048006096012192],AUTHORITY[&amp;quot;EPSG&amp;quot;,26852]]&lt;/WKT&gt;&lt;XOrigin&gt;-119097700&lt;/XOrigin&gt;&lt;YOrigin&gt;-96454900&lt;/YOrigin&gt;&lt;XYScale&gt;37300567.321918227&lt;/XYScale&gt;&lt;ZOrigin&gt;-100000&lt;/ZOrigin&gt;&lt;ZScale&gt;10000&lt;/ZScale&gt;&lt;MOrigin&gt;-100000&lt;/MOrigin&gt;&lt;MScale&gt;10000&lt;/MScale&gt;&lt;XYTolerance&gt;0.0032808333333333335&lt;/XYTolerance&gt;&lt;ZTolerance&gt;0.001&lt;/ZTolerance&gt;&lt;MTolerance&gt;0.001&lt;/MTolerance&gt;&lt;HighPrecision&gt;true&lt;/HighPrecision&gt;&lt;WKID&gt;26852&lt;/WKID&gt;&lt;/ProjectedCoordinateSystem&gt;</peXml><projcsn Sync="TRUE">NAD_1983_StatePlane_Nebraska_FIPS_2600_Feet</projcsn></coordRef><lineage><Process ToolSource="c:\program files (x86)\arcgis\desktop10.0\ArcToolbox\Toolboxes\Conversion Tools.tbx\FeatureClassToFeatureClass" Date="20120418" Time="130953">FeatureClassToFeatureClass C:\doq5\Zipcode\tl_2010_31_zcta510.shp "Database Connections\server23BaseDataNew.sde\basedata.GISWRITER.TigerDerivedData" ZipCode # "STATEFP10 "STATEFP10" true true false 2 Text 0 0 ,First,#,C:\doq5\Zipcode\tl_2010_31_zcta510.shp,STATEFP10,-1,-1;ZCTA5CE10 "ZCTA5CE10" true true false 5 Text 0 0 ,First,#,C:\doq5\Zipcode\tl_2010_31_zcta510.shp,ZCTA5CE10,-1,-1;GEOID10 "GEOID10" true true false 7 Text 0 0 ,First,#,C:\doq5\Zipcode\tl_2010_31_zcta510.shp,GEOID10,-1,-1;CLASSFP10 "CLASSFP10" true true false 2 Text 0 0 ,First,#,C:\doq5\Zipcode\tl_2010_31_zcta510.shp,CLASSFP10,-1,-1;MTFCC10 "MTFCC10" true true false 5 Text 0 0 ,First,#,C:\doq5\Zipcode\tl_2010_31_zcta510.shp,MTFCC10,-1,-1;FUNCSTAT10 "FUNCSTAT10" true true false 1 Text 0 0 ,First,#,C:\doq5\Zipcode\tl_2010_31_zcta510.shp,FUNCSTAT10,-1,-1;ALAND10 "ALAND10" true true false 14 Double 0 14 ,First,#,C:\doq5\Zipcode\tl_2010_31_zcta510.shp,ALAND10,-1,-1;AWATER10 "AWATER10" true true false 14 Double 0 14 ,First,#,C:\doq5\Zipcode\tl_2010_31_zcta510.shp,AWATER10,-1,-1;INTPTLAT10 "INTPTLAT10" true true false 11 Text 0 0 ,First,#,C:\doq5\Zipcode\tl_2010_31_zcta510.shp,INTPTLAT10,-1,-1;INTPTLON10 "INTPTLON10" true true false 12 Text 0 0 ,First,#,C:\doq5\Zipcode\tl_2010_31_zcta510.shp,INTPTLON10,-1,-1;PARTFLG10 "PARTFLG10" true true false 1 Text 0 0 ,First,#,C:\doq5\Zipcode\tl_2010_31_zcta510.shp,PARTFLG10,-1,-1" #</Process><Process ToolSource="c:\program files (x86)\arcgis\desktop10.0\ArcToolbox\Toolboxes\Conversion Tools.tbx\FeatureClassToFeatureClass" Date="20130809" Time="104609">FeatureClassToFeatureClass "Database Connections\BasedataWriter.sde\basedata.GISWRITER.TigerDerivedData\basedata.GISWRITER.ZipCode" C:\doq5\UTM\ZipCodesSP ZipCodesSP.shp # "STATEFP10 "STATEFP10" true true false 2 Text 0 0 ,First,#,Database Connections\BasedataWriter.sde\basedata.GISWRITER.TigerDerivedData\basedata.GISWRITER.ZipCode,STATEFP10,-1,-1;ZCTA5CE10 "ZCTA5CE10" true true false 5 Text 0 0 ,First,#,Database Connections\BasedataWriter.sde\basedata.GISWRITER.TigerDerivedData\basedata.GISWRITER.ZipCode,ZCTA5CE10,-1,-1;GEOID10 "GEOID10" true true false 7 Text 0 0 ,First,#,Database Connections\BasedataWriter.sde\basedata.GISWRITER.TigerDerivedData\basedata.GISWRITER.ZipCode,GEOID10,-1,-1;CLASSFP10 "CLASSFP10" true true false 2 Text 0 0 ,First,#,Database Connections\BasedataWriter.sde\basedata.GISWRITER.TigerDerivedData\basedata.GISWRITER.ZipCode,CLASSFP10,-1,-1;MTFCC10 "MTFCC10" true true false 5 Text 0 0 ,First,#,Database Connections\BasedataWriter.sde\basedata.GISWRITER.TigerDerivedData\basedata.GISWRITER.ZipCode,MTFCC10,-1,-1;FUNCSTAT10 "FUNCSTAT10" true true false 1 Text 0 0 ,First,#,Database Connections\BasedataWriter.sde\basedata.GISWRITER.TigerDerivedData\basedata.GISWRITER.ZipCode,FUNCSTAT10,-1,-1;ALAND10 "ALAND10" true true false 8 Double 0 14 ,First,#,Database Connections\BasedataWriter.sde\basedata.GISWRITER.TigerDerivedData\basedata.GISWRITER.ZipCode,ALAND10,-1,-1;AWATER10 "AWATER10" true true false 8 Double 0 14 ,First,#,Database Connections\BasedataWriter.sde\basedata.GISWRITER.TigerDerivedData\basedata.GISWRITER.ZipCode,AWATER10,-1,-1;INTPTLAT10 "INTPTLAT10" true true false 11 Text 0 0 ,First,#,Database Connections\BasedataWriter.sde\basedata.GISWRITER.TigerDerivedData\basedata.GISWRITER.ZipCode,INTPTLAT10,-1,-1;INTPTLON10 "INTPTLON10" true true false 12 Text 0 0 ,First,#,Database Connections\BasedataWriter.sde\basedata.GISWRITER.TigerDerivedData\basedata.GISWRITER.ZipCode,INTPTLON10,-1,-1;PARTFLG10 "PARTFLG10" true true false 1 Text 0 0 ,First,#,Database Connections\BasedataWriter.sde\basedata.GISWRITER.TigerDerivedData\basedata.GISWRITER.ZipCode,PARTFLG10,-1,-1;Shape_area "Shape.area" false false true 0 Double 0 0 ,First,#,Database Connections\BasedataWriter.sde\basedata.GISWRITER.TigerDerivedData\basedata.GISWRITER.ZipCode,Shape.area,-1,-1;Shape_len "Shape.len" false false true 0 Double 0 0 ,First,#,Database Connections\BasedataWriter.sde\basedata.GISWRITER.TigerDerivedData\basedata.GISWRITER.ZipCode,Shape.len,-1,-1" #</Process></lineage></DataProperties><SyncDate>20130809</SyncDate><SyncTime>10460800</SyncTime><ModDate>20130809</ModDate><ModTime>10460800</ModTime><ArcGISFormat>1.0</ArcGISFormat><ArcGISProfile>FGDC</ArcGISProfile></Esri><mdLang><languageCode value="eng"/><countryCode value="USA" Sync="TRUE"/></mdLang><mdHrLv><ScopeCd value="005"/></mdHrLv><mdContact><rpOrgName>U.S. Department of Commerce, U.S. Census Bureau, Geography Division, Geographic Products Branch</rpOrgName><rpCntInfo><cntPhone><voiceNum>301-763-1128</voiceNum><faxNum>301-763-4710</faxNum></cntPhone><cntAddress addressType="postal"><delPoint>4600 Silver Hill Road, Stop 7400</delPoint><city>Washington</city><adminArea>DC</adminArea><postCode>20233-7400</postCode><country>US</country><eMailAdd>geo.tiger@census.gov</eMailAdd></cntAddress></rpCntInfo><role><RoleCd value="007"/></role></mdContact><mdDateSt Sync="TRUE">20130809</mdDateSt><mdStanName>ArcGIS Metadata</mdStanName><mdStanVer>1.0</mdStanVer><distInfo><distributor><distorCont><rpOrgName>U.S. Department of Commerce, U.S. Census Bureau, Geography Division, Geographic Products Branch</rpOrgName><rpCntInfo><cntPhone><voiceNum>301-763-1128</voiceNum><faxNum>301-763-4710</faxNum></cntPhone><cntAddress addressType="postal"><delPoint>4600 Silver Hill Road, Stop 7400</delPoint><city>Washington</city><adminArea>DC</adminArea><postCode>20233-7400</postCode><country>US</country><eMailAdd>geo.tiger@census.gov</eMailAdd></cntAddress></rpCntInfo><role><RoleCd value="005"/></role></distorCont><distorOrdPrc><resFees>The online copy of the TIGER/Line files may be accessed without charge.</resFees><ordInstr>To obtain more information about ordering TIGER/Line shapefiles visit http://www.census.gov/geo/www/tiger</ordInstr></distorOrdPrc><distorFormat><formatName>TGRSHP (compressed)</formatName><fileDecmTech>PK-ZIP, version 1.93 A or higher</fileDecmTech></distorFormat><distorTran><onLineSrc><linkage>http://www.census.gov/geo/www/tiger</linkage></onLineSrc></distorTran><distorTran><offLineMed><medFormat><MedFormCd value="004"/></medFormat></offLineMed></distorTran></distributor><distTranOps><onLineSrc><linkage>http://www.census.gov/geo/www/tiger</linkage></onLineSrc><transSize Sync="TRUE">0.000</transSize></distTranOps><distFormat><formatName Sync="TRUE">Shapefile</formatName></distFormat></distInfo><dataIdInfo><idCitation><resTitle Sync="FALSE">Nebraska Zip Codes - TIGER 2010</resTitle><date><pubDate>2010-01-01</pubDate></date><resEd>2010</resEd><citRespParty><rpOrgName>U.S. Department of Commerce, U.S. Census Bureau, Geography Division</rpOrgName><role><RoleCd value="006"/></role></citRespParty><presForm><PresFormCd value="005"/></presForm><presForm><fgdcGeoform>vector digital data</fgdcGeoform></presForm><citOnlineRes><linkage>http://www.census.gov/geo/www/tiger</linkage></citOnlineRes></idCitation><idAbs>&lt;DIV STYLE="text-align:Left;"&gt;&lt;DIV&gt;&lt;DIV&gt;&lt;P&gt;&lt;SPAN&gt;The TIGER/Line Files are shapefiles and related database files (.dbf) that are an extract of selected geographic and cartographic information from the U.S. Census Bureau's Master Address File / Topologically Integrated Geographic Encoding and Referencing (MAF/TIGER) Database (MTDB). The MTDB represents a seamless national file with no overlaps or gaps between parts, however, each TIGER/Line File is designed to stand alone as an independent data set, or they can be combined to cover the entire nation. ZIP Code Tabulation Areas (ZCTAs) are approximate area representations of U.S. Postal Service (USPS) ZIP Code service areas that the Census Bureau creates to present statistical data from Census 2000. The Census Bureau creates ZCTAs for the United States, Puerto Rico, American Samoa, Guam, the Commonwealth of the Northern Mariana Islands, and the U.S. Virgin Islands for the 2010 Census. Data users should not use ZCTAs to identify the official USPS ZIP Code for mail delivery. The USPS makes periodic changes to ZIP Codes to support more efficient mail delivery. For the 2010 Census, ZCTAs should more accurately represent the actual ZIP Codes at the time of their delineation than they did for Census 2000. This is because that before the tabulation blocks, which the ZCTAs are built from, were delineated for the 2010 Census, the Census Bureau undertook the process of inserting lines that could be used as 2010 Census tabulation block boundaries, and these lines split polygons where the result would be that a significant number of addresses would occur on either one or both sides of the line associated with a single ZIP Code. Each 2010 Census tabulation block that contains addresses is assigned to a single ZCTA, usually to the ZCTA that reflects the most frequently occurring ZIP Code for the addresses within that tabulation block. As a result, ZIP Codes associated with address ranges found in the Address Ranges relationship file may not always match the ZCTA. Blocks that do not contain addresses but are completely surrounded by a single ZCTA (enclaves) are assigned to the surrounding ZCTA. A ZCTA may not exist for every USPS ZIP Code. Some ZIP Codes may not have a matching ZCTA because too few addresses were associated with the specific ZIP Code or the ZIP Code was not the most frequently occurring ZIP Code within any of the blocks were it exists. The Census Bureau uses the addresses stored within MTDB to delineate ZCTAs, and at the time of the 2010 Census the MTDB primarily included addresses for residential or at least potentially residential structures, so ZCTAs representing only non-residential structures are infrequent. Also, in each tabulation block, if a choice existed between using a potential city-style mail delivery ZIP Code for an address or a post office box ZIP Code, the city-style mail delivery ZIP Code was preferred for the 2010 Census ZCTA delineation. The Census Bureau identifies 5-digit ZCTAs using a five-character numeric code that represents the most frequently occurring USPS ZIP Code within that ZCTA, and this code may contain leading zeros.&lt;/SPAN&gt;&lt;/P&gt;&lt;/DIV&gt;&lt;/DIV&gt;&lt;/DIV&gt;</idAbs><idPurp>In order for others to use the information in the Census MAF/TIGER database in a geographic information system (GIS) or for other geographic applications, the Census Bureau releases to the public extracts of the database in the form of TIGER/Line Shapefiles.</idPurp><idStatus><ProgCd value="001"/></idStatus><idPoC><rpOrgName>U.S. Department of Commerce, U.S. Census Bureau, Geography Division, Geographic Products Branch</rpOrgName><rpCntInfo><cntPhone><voiceNum>301-763-1128</voiceNum><faxNum>301-763-4710</faxNum></cntPhone><cntAddress addressType="postal"><delPoint>4600 Silver Hill Road, Stop 7400</delPoint><city>Washington</city><adminArea>DC</adminArea><postCode>20233-7400</postCode><country>US</country><eMailAdd>geo.tiger@census.gov</eMailAdd></cntAddress></rpCntInfo><role><RoleCd value="007"/></role></idPoC><placeKeys><thesaName><resTitle>INCITS.38-200x (R2004),INCITS.31-200x (R2007),INCITS.454-200x,INCITS 455-200x,INCITS 446-2008</resTitle></thesaName><keyword>Nebraska</keyword><keyword>31</keyword><keyword>United States</keyword><keyword>U.S.</keyword><keyword>NE</keyword><keyword>State or Equivalent Entity</keyword></placeKeys><themeKeys><keyword>ZIP Code Tabulation Area</keyword><keyword>ZCTA</keyword><keyword>Polygon</keyword><keyword>State or equivalent entity</keyword><keyword>Zip Code</keyword></themeKeys><themeKeys><thesaName><resTitle>ISO 19115 Topic Categories</resTitle></thesaName><keyword>boundaries</keyword></themeKeys><searchKeys><keyword>Nebraska</keyword><keyword>ZIP Code Tabulation Area</keyword><keyword>31</keyword><keyword>United States</keyword><keyword>U.S.</keyword><keyword>ZCTA</keyword><keyword>Polygon</keyword><keyword>State or equivalent entity</keyword><keyword>boundaries</keyword><keyword>NE</keyword><keyword>Zip Code</keyword><keyword>State or Equivalent Entity</keyword></searchKeys><resConst><LegConsts><useLimit>No warranty, expressed or implied is made with regard to the accuracy of these data, and no liability is assumed by the U.S. Government in general or the U.S. Census Bureau in specific as to the spatial or attribute accuracy of the data. The act of distribution shall not constitute any such warranty and no responsibility is assumed by the U.S. government in the use of these files. The boundary information in the TIGER/Line Shapefiles is for statistical data collection and tabulation purposes only; their depiction and designation for statistical purposes do not constitute a determination of jurisdictional authority or rights of ownership or entitlement and they are not legal land descriptions.</useLimit></LegConsts></resConst><resConst><Consts><useLimit>The TIGER/Line Shapefile products are not copyrighted however TIGER/Line and Census TIGER are registered trademarks of the U.S. Census Bureau. These products are free to use in a product or publication, however acknowledgement must be given to the U.S. Census Bureau as the source. The boundary information in the TIGER/Line Shapefiles are for statistical data collection and tabulation purposes only; their depiction and designation for statistical purposes does not constitute a determination of jurisdictional authority or rights of ownership or entitlement and they are not legal land descriptions.Coordinates in the TIGER/Line shapefiles have six implied decimal places, but the positional accuracy of these coordinates is not as great as the six decimal places suggest.</useLimit></Consts></resConst><spatRpType><SpatRepTypCd value="001"/></spatRpType><dataLang><languageCode value="eng"/><countryCode value="USA" Sync="TRUE"/></dataLang><dataExt><exDesc>Publication Date</exDesc><tempEle><TempExtent><exTemp><TM_Period><tmBegin>2010-01-01</tmBegin><tmEnd>2010-07-01</tmEnd></TM_Period></exTemp></TempExtent></tempEle></dataExt><dataExt><geoEle><GeoBndBox><westBL>-104.053514</westBL><eastBL>-95.30829</eastBL><southBL>39.999932</southBL><northBL>43.001707</northBL></GeoBndBox></geoEle></dataExt><envirDesc Sync="TRUE">Microsoft Windows 7 Version 6.1 (Build 7601) Service Pack 1; ESRI ArcGIS 10.0.5.4400</envirDesc><dataExt><geoEle><GeoBndBox esriExtentType="search"><exTypeCode Sync="TRUE">1</exTypeCode><westBL Sync="TRUE">-104.180689</westBL><eastBL Sync="TRUE">-95.088856</eastBL><northBL Sync="TRUE">43.070299</northBL><southBL Sync="TRUE">39.903782</southBL></GeoBndBox></geoEle></dataExt><tpCat><TopicCatCd value="003"/></tpCat></dataIdInfo><dqInfo><dqScope><scpLvl><ScopeCd value="005"/></scpLvl></dqScope><report type="DQConcConsis"><measDesc>The Census Bureau performed automated tests to ensure logical consistency and limits of shapefiles. Segments making up the outer and inner boundaries of a polygon tie end-to-end to completely enclose the area. All polygons are tested for closure. The Census Bureau uses its internally developed geographic update system to enhance and modify spatial and attribute data in the Census MAF/TIGER database. Standard geographic codes, such as FIPS codes for states, counties, municipalities, county subdivisions, places, American Indian/Alaska Native/Native Hawaiian areas, and congressional districts are used when encoding spatial entities. The Census Bureau performed spatial data tests for logical consistency of the codes during the compilation of the original Census MAF/TIGER database files. Most of the codes for geographic entities except states, counties, urban areas, Core Based Statistical Areas (CBSAs), American Indian Areas (AIAs), and congressional districts were provided to the Census Bureau by the USGS, the agency responsible for maintaining FIPS 55. Feature attribute information has been examined but has not been fully tested for consistency. For the TIGER/Line Shapefiles, the Point and Vector Object Count for the G-polygon SDTS Point and Vector Object Type reflects the number of records in the shapefile attribute table. For multi-polygon features, only one attribute record exists for each multi-polygon rather than one attribute record per individual G-polygon component of the multi-polygon feature. TIGER/Line Shapefile multi-polygons are an exception to the G-polygon object type classification. Therefore, when multi-polygons exist in a shapefile, the object count will be less than the actual number of G-polygons.</measDesc></report><report type="DQCompOm"><measDesc>Data completeness of the TIGER/Line Shapefiles reflects the contents of the Census MAF/TIGER database at the time the TIGER/Line Shapefiles were created.</measDesc></report><report type="DQQuanAttAcc"><measDesc>Accurate against Federal Information Processing Standards (FIPS), FIPS Publication 6-4, and FIPS-55 at the 100% level for the codes and base names. The remaining attribute information has been examined but has not been fully tested for accuracy.</measDesc></report><dataLineage><prcStep><stepDesc>TIGER/Line Shapefiles are extracted from the Census MAF/TIGER database by nation, state, county, and entity. Census MAF/TIGER data for all of the aforementioned geographic entities are then distributed among the shapefiles each containing attributes for line, polygon, or landmark geographic data.</stepDesc><stepDateTm>2010-01-01</stepDateTm><stepSrc type="used"><srcCitatn><resAltTitle>Census MAF/TIGER</resAltTitle></srcCitatn></stepSrc></prcStep><dataSource><srcDesc>The selected geographic and cartographic information (line segments) are derived from the U.S. Census Bureau's Master Address File Topologically Integrated Geographic Encoding and Referencing (MAF/TIGER) database.</srcDesc><srcMedName><MedNameCd value="015"/></srcMedName><srcCitatn><resTitle>Census MAF/TIGER database</resTitle><resAltTitle>MAF/TIGER</resAltTitle><date><pubDate date="inapplicable"/></date><citRespParty><rpOrgName>U.S. Department of Commerce, U.S. Census Bureau, Geography Division</rpOrgName><role><RoleCd value="006"/></role></citRespParty></srcCitatn><srcExt><exDesc>Publication Date</exDesc><tempEle><TempExtent><exTemp><TM_Period><tmBegin>2010-01-01</tmBegin><tmEnd>2010-07-01</tmEnd></TM_Period></exTemp></TempExtent></tempEle></srcExt></dataSource></dataLineage></dqInfo><spatRepInfo><Indref>Federal Information Processing Standards (FIPS), ANSI, and feature names.</Indref><VectSpatRep><geometObjs Name="ZipCodesSP"><geoObjTyp><GeoObjTypCd value="002" Sync="TRUE"></GeoObjTypCd></geoObjTyp><geoObjCnt Sync="TRUE">0</geoObjCnt></geometObjs><topLvl><TopoLevCd value="001" Sync="TRUE"></TopoLevCd></topLvl></VectSpatRep></spatRepInfo><Binary><Enclosure><Descript>original metadata</Descript><Data SourceMetadata="yes" OriginalFileName="source_metadata.xml" SourceMetadataDigest="cbc9f54a73639be45bd683c7303bbb" EsriPropertyType="Base64" SourceMetadataSchema="fgdc">PD94bWwgdmVyc2lvbj0iMS4wIiBlbmNvZGluZz0idXRmLTgiPz4NCjxtZXRhZGF0YT4NCiAgPGlk
aW5mbz4NCiAgICA8Y2l0YXRpb24+DQogICAgICA8Y2l0ZWluZm8+DQogICAgICAgIDxvcmlnaW4+
VS5TLiBEZXBhcnRtZW50IG9mIENvbW1lcmNlLCBVLlMuIENlbnN1cyBCdXJlYXUsIEdlb2dyYXBo
eSBEaXZpc2lvbjwvb3JpZ2luPg0KICAgICAgICA8cHViZGF0ZT4yMDEwPC9wdWJkYXRlPg0KICAg
ICAgICA8dGl0bGU+VElHRVIvTGluZSBTaGFwZWZpbGUsIDIwMTAsIDIwMTAgc3RhdGUsIE5lYnJh
c2thLCAyMDEwIENlbnN1cyA1LURpZ2l0IFpJUCBDb2RlIFRhYnVsYXRpb24gQXJlYSAoWkNUQTUp
IFN0YXRlLWJhc2VkPC90aXRsZT4NCiAgICAgICAgPGVkaXRpb24+MjAxMDwvZWRpdGlvbj4NCiAg
ICAgICAgPGdlb2Zvcm0+dmVjdG9yIGRpZ2l0YWwgZGF0YTwvZ2VvZm9ybT4NCiAgICAgICAgPG9u
bGluaz5odHRwOi8vd3d3LmNlbnN1cy5nb3YvZ2VvL3d3dy90aWdlcjwvb25saW5rPg0KICAgICAg
PC9jaXRlaW5mbz4NCiAgICA8L2NpdGF0aW9uPg0KICAgIDxkZXNjcmlwdD4NCiAgICAgIDxhYnN0
cmFjdD5UaGUgVElHRVIvTGluZSBGaWxlcyBhcmUgc2hhcGVmaWxlcyBhbmQgcmVsYXRlZCBkYXRh
YmFzZSBmaWxlcyAoLmRiZikgdGhhdCBhcmUgYW4gZXh0cmFjdCBvZiBzZWxlY3RlZCBnZW9ncmFw
aGljIGFuZCBjYXJ0b2dyYXBoaWMgaW5mb3JtYXRpb24gZnJvbSB0aGUgVS5TLiBDZW5zdXMgQnVy
ZWF1J3MgTWFzdGVyIEFkZHJlc3MgRmlsZSAvIFRvcG9sb2dpY2FsbHkgSW50ZWdyYXRlZCBHZW9n
cmFwaGljIEVuY29kaW5nIGFuZCBSZWZlcmVuY2luZyAoTUFGL1RJR0VSKSBEYXRhYmFzZSAoTVRE
QikuICBUaGUgTVREQiByZXByZXNlbnRzIGEgc2VhbWxlc3MgbmF0aW9uYWwgZmlsZSB3aXRoIG5v
IG92ZXJsYXBzIG9yIGdhcHMgYmV0d2VlbiBwYXJ0cywgaG93ZXZlciwgZWFjaCBUSUdFUi9MaW5l
IEZpbGUgaXMgZGVzaWduZWQgdG8gc3RhbmQgYWxvbmUgYXMgYW4gaW5kZXBlbmRlbnQgZGF0YSBz
ZXQsIG9yIHRoZXkgY2FuIGJlIGNvbWJpbmVkIHRvIGNvdmVyIHRoZSBlbnRpcmUgbmF0aW9uLiAg
ICBaSVAgQ29kZSBUYWJ1bGF0aW9uIEFyZWFzIChaQ1RBcykgYXJlIGFwcHJveGltYXRlIGFyZWEg
cmVwcmVzZW50YXRpb25zIG9mIFUuUy4gUG9zdGFsIFNlcnZpY2UgKFVTUFMpIFpJUCBDb2RlIHNl
cnZpY2UgYXJlYXMgdGhhdCB0aGUgQ2Vuc3VzIEJ1cmVhdSBjcmVhdGVzIHRvIHByZXNlbnQgc3Rh
dGlzdGljYWwgZGF0YSBmcm9tIENlbnN1cyAyMDAwLiAgVGhlIENlbnN1cyBCdXJlYXUgY3JlYXRl
cyBaQ1RBcyBmb3IgdGhlIFVuaXRlZCBTdGF0ZXMsIFB1ZXJ0byBSaWNvLCBBbWVyaWNhbiBTYW1v
YSwgR3VhbSwgdGhlIENvbW1vbndlYWx0aCBvZiB0aGUgTm9ydGhlcm4gTWFyaWFuYSBJc2xhbmRz
LCBhbmQgdGhlIFUuUy4gVmlyZ2luIElzbGFuZHMgZm9yIHRoZSAyMDEwIENlbnN1cy4gIERhdGEg
dXNlcnMgc2hvdWxkIG5vdCB1c2UgWkNUQXMgdG8gaWRlbnRpZnkgdGhlIG9mZmljaWFsIFVTUFMg
WklQIENvZGUgZm9yIG1haWwgZGVsaXZlcnkuICBUaGUgVVNQUyBtYWtlcyBwZXJpb2RpYyBjaGFu
Z2VzIHRvIFpJUCBDb2RlcyB0byBzdXBwb3J0IG1vcmUgZWZmaWNpZW50IG1haWwgZGVsaXZlcnku
ICBGb3IgdGhlIDIwMTAgQ2Vuc3VzLCBaQ1RBcyBzaG91bGQgbW9yZSBhY2N1cmF0ZWx5IHJlcHJl
c2VudCB0aGUgYWN0dWFsIFpJUCBDb2RlcyBhdCB0aGUgdGltZSBvZiB0aGVpciBkZWxpbmVhdGlv
biB0aGFuIHRoZXkgZGlkIGZvciBDZW5zdXMgMjAwMC4gIFRoaXMgaXMgYmVjYXVzZSB0aGF0IGJl
Zm9yZSB0aGUgdGFidWxhdGlvbiBibG9ja3MsIHdoaWNoIHRoZSBaQ1RBcyBhcmUgYnVpbHQgZnJv
bSwgd2VyZSBkZWxpbmVhdGVkIGZvciB0aGUgMjAxMCBDZW5zdXMsIHRoZSBDZW5zdXMgQnVyZWF1
IHVuZGVydG9vayB0aGUgcHJvY2VzcyBvZiBpbnNlcnRpbmcgbGluZXMgdGhhdCBjb3VsZCBiZSB1
c2VkIGFzIDIwMTAgQ2Vuc3VzIHRhYnVsYXRpb24gYmxvY2sgYm91bmRhcmllcywgYW5kIHRoZXNl
IGxpbmVzIHNwbGl0IHBvbHlnb25zIHdoZXJlIHRoZSByZXN1bHQgd291bGQgYmUgdGhhdCBhIHNp
Z25pZmljYW50IG51bWJlciBvZiBhZGRyZXNzZXMgd291bGQgb2NjdXIgb24gZWl0aGVyIG9uZSBv
ciBib3RoIHNpZGVzIG9mIHRoZSBsaW5lIGFzc29jaWF0ZWQgd2l0aCBhIHNpbmdsZSBaSVAgQ29k
ZS4gIEVhY2ggMjAxMCBDZW5zdXMgdGFidWxhdGlvbiBibG9jayB0aGF0IGNvbnRhaW5zIGFkZHJl
c3NlcyBpcyBhc3NpZ25lZCB0byBhIHNpbmdsZSBaQ1RBLCB1c3VhbGx5IHRvIHRoZSBaQ1RBIHRo
YXQgcmVmbGVjdHMgdGhlIG1vc3QgZnJlcXVlbnRseSBvY2N1cnJpbmcgWklQIENvZGUgZm9yIHRo
ZSBhZGRyZXNzZXMgd2l0aGluIHRoYXQgdGFidWxhdGlvbiBibG9jay4gIEFzIGEgcmVzdWx0LCBa
SVAgQ29kZXMgYXNzb2NpYXRlZCB3aXRoIGFkZHJlc3MgcmFuZ2VzIGZvdW5kIGluIHRoZSBBZGRy
ZXNzIFJhbmdlcyByZWxhdGlvbnNoaXAgZmlsZSBtYXkgbm90IGFsd2F5cyBtYXRjaCB0aGUgWkNU
QS4gIEJsb2NrcyB0aGF0IGRvIG5vdCBjb250YWluIGFkZHJlc3NlcyBidXQgYXJlIGNvbXBsZXRl
bHkgc3Vycm91bmRlZCBieSBhIHNpbmdsZSBaQ1RBIChlbmNsYXZlcykgYXJlIGFzc2lnbmVkIHRv
IHRoZSBzdXJyb3VuZGluZyBaQ1RBLiAgQSBaQ1RBIG1heSBub3QgZXhpc3QgZm9yIGV2ZXJ5IFVT
UFMgWklQIENvZGUuICBTb21lIFpJUCBDb2RlcyBtYXkgbm90IGhhdmUgYSBtYXRjaGluZyBaQ1RB
IGJlY2F1c2UgdG9vIGZldyBhZGRyZXNzZXMgd2VyZSBhc3NvY2lhdGVkIHdpdGggdGhlIHNwZWNp
ZmljIFpJUCBDb2RlIG9yIHRoZSBaSVAgQ29kZSB3YXMgbm90IHRoZSBtb3N0IGZyZXF1ZW50bHkg
b2NjdXJyaW5nIFpJUCBDb2RlIHdpdGhpbiBhbnkgb2YgdGhlIGJsb2NrcyB3ZXJlIGl0IGV4aXN0
cy4gIFRoZSBDZW5zdXMgQnVyZWF1IHVzZXMgdGhlIGFkZHJlc3NlcyBzdG9yZWQgd2l0aGluIE1U
REIgdG8gZGVsaW5lYXRlIFpDVEFzLCBhbmQgYXQgdGhlIHRpbWUgb2YgdGhlIDIwMTAgQ2Vuc3Vz
IHRoZSBNVERCIHByaW1hcmlseSBpbmNsdWRlZCBhZGRyZXNzZXMgZm9yIHJlc2lkZW50aWFsIG9y
IGF0IGxlYXN0IHBvdGVudGlhbGx5IHJlc2lkZW50aWFsIHN0cnVjdHVyZXMsIHNvIFpDVEFzIHJl
cHJlc2VudGluZyBvbmx5IG5vbi1yZXNpZGVudGlhbCBzdHJ1Y3R1cmVzIGFyZSBpbmZyZXF1ZW50
LiAgQWxzbywgaW4gZWFjaCB0YWJ1bGF0aW9uIGJsb2NrLCBpZiBhIGNob2ljZSBleGlzdGVkIGJl
dHdlZW4gdXNpbmcgYSBwb3RlbnRpYWwgY2l0eS1zdHlsZSBtYWlsIGRlbGl2ZXJ5IFpJUCBDb2Rl
IGZvciBhbiBhZGRyZXNzIG9yIGEgcG9zdCBvZmZpY2UgYm94IFpJUCBDb2RlLCB0aGUgY2l0eS1z
dHlsZSBtYWlsIGRlbGl2ZXJ5IFpJUCBDb2RlIHdhcyBwcmVmZXJyZWQgZm9yIHRoZSAyMDEwIENl
bnN1cyBaQ1RBIGRlbGluZWF0aW9uLiAgVGhlIENlbnN1cyBCdXJlYXUgaWRlbnRpZmllcyA1LWRp
Z2l0IFpDVEFzIHVzaW5nIGEgZml2ZS1jaGFyYWN0ZXIgbnVtZXJpYyBjb2RlIHRoYXQgcmVwcmVz
ZW50cyB0aGUgbW9zdCBmcmVxdWVudGx5IG9jY3VycmluZyBVU1BTIFpJUCBDb2RlIHdpdGhpbiB0
aGF0IFpDVEEsIGFuZCB0aGlzIGNvZGUgbWF5IGNvbnRhaW4gbGVhZGluZyB6ZXJvcy4gIA0KPC9h
YnN0cmFjdD4NCiAgICAgIDxwdXJwb3NlPkluIG9yZGVyIGZvciBvdGhlcnMgdG8gdXNlIHRoZSBp
bmZvcm1hdGlvbiBpbiB0aGUgQ2Vuc3VzIE1BRi9USUdFUiBkYXRhYmFzZSBpbiBhIGdlb2dyYXBo
aWMgaW5mb3JtYXRpb24gc3lzdGVtIChHSVMpIG9yIGZvciBvdGhlciBnZW9ncmFwaGljIGFwcGxp
Y2F0aW9ucywgdGhlIENlbnN1cyBCdXJlYXUgcmVsZWFzZXMgdG8gdGhlIHB1YmxpYyBleHRyYWN0
cyBvZiB0aGUgZGF0YWJhc2UgaW4gdGhlIGZvcm0gb2YgVElHRVIvTGluZSBTaGFwZWZpbGVzLjwv
cHVycG9zZT4NCiAgICAgIDxTdWJqZWN0X0VudGl0eT5OZWJyYXNrYSgzMSk8L1N1YmplY3RfRW50
aXR5Pg0KICAgIDwvZGVzY3JpcHQ+DQogICAgPHRpbWVwZXJkPg0KICAgICAgPHRpbWVpbmZvPg0K
ICAgICAgICA8cm5nZGF0ZXM+DQogICAgICAgICAgPGJlZ2RhdGU+MjAxMDAxPC9iZWdkYXRlPg0K
ICAgICAgICAgIDxlbmRkYXRlPjIwMTAwNzwvZW5kZGF0ZT4NCiAgICAgICAgPC9ybmdkYXRlcz4N
CiAgICAgIDwvdGltZWluZm8+DQogICAgICA8Y3VycmVudD5QdWJsaWNhdGlvbiBEYXRlPC9jdXJy
ZW50Pg0KICAgIDwvdGltZXBlcmQ+DQogICAgPHN0YXR1cz4NCiAgICAgIDxwcm9ncmVzcz5Db21w
bGV0ZTwvcHJvZ3Jlc3M+DQogICAgICA8dXBkYXRlPlRJR0VSL0xpbmUgU2hhcGVmaWxlcyBhcmUg
ZXh0cmFjdGVkIGZyb20gdGhlIENlbnN1cyBNQUYvVElHRVIgZGF0YWJhc2UuICBObyBjaGFuZ2Vz
IG9yIHVwZGF0ZXMgd2lsbCBiZSBtYWRlIHRvIHRoaXMgdmVyc2lvbiBvZiB0aGUgVElHRVIvTGlu
ZSBTaGFwZWZpbGVzLiAgRnV0dXJlIHJlbGVhc2VzIG9mIFRJR0VSL0xpbmUgU2hhcGVmaWxlcyB3
aWxsIHJlZmxlY3QgdXBkYXRlcyBtYWRlIHRvIHRoZSBDZW5zdXMgTUFGL1RJR0VSIGRhdGFiYXNl
LjwvdXBkYXRlPg0KICAgIDwvc3RhdHVzPg0KICAgIDxzcGRvbT4NCiAgICAgIDxib3VuZGluZz4N
CiAgICAgICAgPHdlc3RiYz4tMTA0LjA1MzUxNDwvd2VzdGJjPg0KICAgICAgICA8ZWFzdGJjPi05
NS4zMDgyOTwvZWFzdGJjPg0KICAgICAgICA8bm9ydGhiYz40My4wMDE3MDc8L25vcnRoYmM+DQog
ICAgICAgIDxzb3V0aGJjPjM5Ljk5OTkzMjwvc291dGhiYz4NCiAgICAgIDwvYm91bmRpbmc+DQog
ICAgPC9zcGRvbT4NCiAgICA8a2V5d29yZHM+DQogICAgICA8dGhlbWU+DQogICAgICAgIDx0aGVt
ZWt0PklTTyAxOTExNSBUb3BpYyBDYXRlZ29yaWVzPC90aGVtZWt0Pg0KICAgICAgICA8dGhlbWVr
ZXk+Ym91bmRhcmllczwvdGhlbWVrZXk+DQogICAgICA8L3RoZW1lPg0KICAgICAgPHRoZW1lPg0K
ICAgICAgICA8dGhlbWVrdD5Ob25lPC90aGVtZWt0Pg0KICAgICAgICA8dGhlbWVrZXk+U3RhdGUg
b3IgZXF1aXZhbGVudCBlbnRpdHk8L3RoZW1la2V5Pg0KICAgICAgICA8dGhlbWVrZXk+UG9seWdv
bjwvdGhlbWVrZXk+DQogICAgICAgIDx0aGVtZWtleT5aSVAgQ29kZSBUYWJ1bGF0aW9uIEFyZWE8
L3RoZW1la2V5Pg0KICAgICAgICA8dGhlbWVrZXk+WkNUQTwvdGhlbWVrZXk+DQogICAgICAgIDx0
aGVtZWtleT5aaXAgQ29kZTwvdGhlbWVrZXk+DQogICAgICA8L3RoZW1lPg0KICAgICAgPHBsYWNl
Pg0KICAgICAgICA8cGxhY2VrdD5JTkNJVFMuMzgtMjAweCAoUjIwMDQpLElOQ0lUUy4zMS0yMDB4
IChSMjAwNyksSU5DSVRTLjQ1NC0yMDB4LElOQ0lUUyA0NTUtMjAweCxJTkNJVFMgNDQ2LTIwMDg8
L3BsYWNla3Q+DQogICAgICAgIDxwbGFjZWtleT5Vbml0ZWQgU3RhdGVzPC9wbGFjZWtleT4NCiAg
ICAgICAgPHBsYWNla2V5PlUuUy48L3BsYWNla2V5Pg0KICAgICAgICA8cGxhY2VrZXk+U3RhdGUg
b3IgRXF1aXZhbGVudCBFbnRpdHk8L3BsYWNla2V5Pg0KICAgICAgICA8cGxhY2VrZXk+TmVicmFz
a2E8L3BsYWNla2V5Pg0KICAgICAgICA8cGxhY2VrZXk+TkU8L3BsYWNla2V5Pg0KICAgICAgICA8
cGxhY2VrZXk+MzE8L3BsYWNla2V5Pg0KICAgICAgPC9wbGFjZT4NCiAgICA8L2tleXdvcmRzPg0K
ICAgIDxhY2Njb25zdD5Ob25lPC9hY2Njb25zdD4NCiAgICA8dXNlY29uc3Q+VGhlIFRJR0VSL0xp
bmUgU2hhcGVmaWxlIHByb2R1Y3RzIGFyZSBub3QgY29weXJpZ2h0ZWQgaG93ZXZlciBUSUdFUi9M
aW5lIGFuZCBDZW5zdXMgVElHRVIgYXJlIHJlZ2lzdGVyZWQgdHJhZGVtYXJrcyBvZiB0aGUgVS5T
LiBDZW5zdXMgQnVyZWF1LiAgVGhlc2UgcHJvZHVjdHMgYXJlIGZyZWUgdG8gdXNlIGluIGEgcHJv
ZHVjdCBvciBwdWJsaWNhdGlvbiwgaG93ZXZlciBhY2tub3dsZWRnZW1lbnQgbXVzdCBiZSBnaXZl
biB0byB0aGUgVS5TLiBDZW5zdXMgQnVyZWF1IGFzIHRoZSBzb3VyY2UuDQpUaGUgYm91bmRhcnkg
aW5mb3JtYXRpb24gaW4gdGhlIFRJR0VSL0xpbmUgU2hhcGVmaWxlcyBhcmUgZm9yIHN0YXRpc3Rp
Y2FsIGRhdGEgY29sbGVjdGlvbiBhbmQgdGFidWxhdGlvbiBwdXJwb3NlcyBvbmx5OyB0aGVpciBk
ZXBpY3Rpb24gYW5kIGRlc2lnbmF0aW9uIGZvciBzdGF0aXN0aWNhbCBwdXJwb3NlcyBkb2VzIG5v
dCBjb25zdGl0dXRlIGEgZGV0ZXJtaW5hdGlvbiBvZiBqdXJpc2RpY3Rpb25hbCBhdXRob3JpdHkg
b3IgcmlnaHRzIG9mIG93bmVyc2hpcCBvciBlbnRpdGxlbWVudCBhbmQgdGhleSBhcmUgbm90IGxl
Z2FsIGxhbmQgZGVzY3JpcHRpb25zLkNvb3JkaW5hdGVzIGluIHRoZSBUSUdFUi9MaW5lIHNoYXBl
ZmlsZXMgaGF2ZSBzaXggaW1wbGllZCBkZWNpbWFsIHBsYWNlcywgYnV0IHRoZSBwb3NpdGlvbmFs
IGFjY3VyYWN5IG9mIHRoZXNlIGNvb3JkaW5hdGVzIGlzIG5vdCBhcyBncmVhdCBhcyB0aGUgc2l4
IGRlY2ltYWwgcGxhY2VzIHN1Z2dlc3QuPC91c2Vjb25zdD4NCiAgICA8VGl0bGVfMTNfUmVzdHJp
Y3Rpb25zPlllcywgdGhlIGRhdGEgYXJlIGZyZWUgZnJvbSBUaXRsZSAxMyByZXN0cmljdGlvbnM8
L1RpdGxlXzEzX1Jlc3RyaWN0aW9ucz4NCiAgICA8cHRjb250YWM+DQogICAgICA8Y250aW5mbz4N
CiAgICAgICAgPGNudG9yZ3A+DQogICAgICAgICAgPGNudG9yZz5VLlMuIERlcGFydG1lbnQgb2Yg
Q29tbWVyY2UsIFUuUy4gQ2Vuc3VzIEJ1cmVhdSwgR2VvZ3JhcGh5IERpdmlzaW9uLCBHZW9ncmFw
aGljIFByb2R1Y3RzIEJyYW5jaDwvY250b3JnPg0KICAgICAgICA8L2NudG9yZ3A+DQogICAgICAg
IDxjbnRhZGRyPg0KICAgICAgICAgIDxhZGRydHlwZT5NYWlsaW5nIGFkZHJlc3M8L2FkZHJ0eXBl
Pg0KICAgICAgICAgIDxhZGRyZXNzPjQ2MDAgU2lsdmVyIEhpbGwgUm9hZCwgU3RvcCA3NDAwPC9h
ZGRyZXNzPg0KICAgICAgICAgIDxjaXR5Pldhc2hpbmd0b248L2NpdHk+DQogICAgICAgICAgPHN0
YXRlPkRDPC9zdGF0ZT4NCiAgICAgICAgICA8cG9zdGFsPjIwMjMzLTc0MDA8L3Bvc3RhbD4NCiAg
ICAgICAgICA8Y291bnRyeT5Vbml0ZWQgU3RhdGVzPC9jb3VudHJ5Pg0KICAgICAgICA8L2NudGFk
ZHI+DQogICAgICAgIDxjbnR2b2ljZT4zMDEtNzYzLTExMjg8L2NudHZvaWNlPg0KICAgICAgICA8
Y250ZmF4PjMwMS03NjMtNDcxMDwvY250ZmF4Pg0KICAgICAgICA8Y250ZW1haWw+Z2VvLnRpZ2Vy
QGNlbnN1cy5nb3Y8L2NudGVtYWlsPg0KICAgICAgPC9jbnRpbmZvPg0KICAgIDwvcHRjb250YWM+
DQogIDwvaWRpbmZvPg0KICA8RGF0YV9TZXRfQ2hhcmFjdGVyX1NldD44ODU5cGFydDE8L0RhdGFf
U2V0X0NoYXJhY3Rlcl9TZXQ+DQogIDxEYXRhX1NldF9MYW5ndWFnZT5lbmc8L0RhdGFfU2V0X0xh
bmd1YWdlPg0KICA8ZGF0YXF1YWw+DQogICAgPGF0dHJhY2M+DQogICAgICA8YXR0cmFjY3I+QWNj
dXJhdGUgYWdhaW5zdCBGZWRlcmFsIEluZm9ybWF0aW9uIFByb2Nlc3NpbmcgU3RhbmRhcmRzIChG
SVBTKSwgRklQUyBQdWJsaWNhdGlvbiA2LTQsIGFuZCBGSVBTLTU1IGF0IHRoZSAxMDAlIGxldmVs
IGZvciB0aGUgY29kZXMgYW5kIGJhc2UgbmFtZXMuICBUaGUgcmVtYWluaW5nIGF0dHJpYnV0ZSBp
bmZvcm1hdGlvbiBoYXMgYmVlbiBleGFtaW5lZCBidXQgaGFzIG5vdCBiZWVuIGZ1bGx5IHRlc3Rl
ZCBmb3IgYWNjdXJhY3kuPC9hdHRyYWNjcj4NCiAgICA8L2F0dHJhY2M+DQogICAgPGxvZ2ljPlRo
ZSBDZW5zdXMgQnVyZWF1IHBlcmZvcm1lZCBhdXRvbWF0ZWQgdGVzdHMgdG8gZW5zdXJlIGxvZ2lj
YWwgY29uc2lzdGVuY3kgYW5kIGxpbWl0cyBvZiBzaGFwZWZpbGVzLiAgU2VnbWVudHMgbWFraW5n
IHVwIHRoZSBvdXRlciBhbmQgaW5uZXIgYm91bmRhcmllcyBvZiBhIHBvbHlnb24gdGllIGVuZC10
by1lbmQgdG8gY29tcGxldGVseSBlbmNsb3NlIHRoZSBhcmVhLiAgQWxsIHBvbHlnb25zIGFyZSB0
ZXN0ZWQgZm9yIGNsb3N1cmUuDQpUaGUgQ2Vuc3VzIEJ1cmVhdSB1c2VzIGl0cyBpbnRlcm5hbGx5
IGRldmVsb3BlZCBnZW9ncmFwaGljIHVwZGF0ZSBzeXN0ZW0gdG8gZW5oYW5jZSBhbmQgbW9kaWZ5
IHNwYXRpYWwgYW5kIGF0dHJpYnV0ZSBkYXRhIGluIHRoZSBDZW5zdXMgTUFGL1RJR0VSIGRhdGFi
YXNlLiAgU3RhbmRhcmQgZ2VvZ3JhcGhpYyBjb2Rlcywgc3VjaCBhcyBGSVBTIGNvZGVzIGZvciBz
dGF0ZXMsIGNvdW50aWVzLCBtdW5pY2lwYWxpdGllcywgY291bnR5IHN1YmRpdmlzaW9ucywgcGxh
Y2VzLCBBbWVyaWNhbiBJbmRpYW4vQWxhc2thIE5hdGl2ZS9OYXRpdmUgSGF3YWlpYW4gYXJlYXMs
IGFuZCBjb25ncmVzc2lvbmFsIGRpc3RyaWN0cyBhcmUgdXNlZCB3aGVuIGVuY29kaW5nIHNwYXRp
YWwgZW50aXRpZXMuICBUaGUgQ2Vuc3VzIEJ1cmVhdSBwZXJmb3JtZWQgc3BhdGlhbCBkYXRhIHRl
c3RzIGZvciBsb2dpY2FsIGNvbnNpc3RlbmN5IG9mIHRoZSBjb2RlcyBkdXJpbmcgdGhlIGNvbXBp
bGF0aW9uIG9mIHRoZSBvcmlnaW5hbCBDZW5zdXMgTUFGL1RJR0VSIGRhdGFiYXNlIGZpbGVzLiAg
TW9zdCBvZiB0aGUgY29kZXMgZm9yIGdlb2dyYXBoaWMgZW50aXRpZXMgZXhjZXB0IHN0YXRlcywg
Y291bnRpZXMsIHVyYmFuIGFyZWFzLCBDb3JlIEJhc2VkIFN0YXRpc3RpY2FsIEFyZWFzIChDQlNB
cyksIEFtZXJpY2FuIEluZGlhbiBBcmVhcyAoQUlBcyksIGFuZCBjb25ncmVzc2lvbmFsIGRpc3Ry
aWN0cyB3ZXJlIHByb3ZpZGVkIHRvIHRoZSBDZW5zdXMgQnVyZWF1IGJ5IHRoZSBVU0dTLCB0aGUg
YWdlbmN5IHJlc3BvbnNpYmxlIGZvciBtYWludGFpbmluZyBGSVBTIDU1LiAgRmVhdHVyZSBhdHRy
aWJ1dGUgaW5mb3JtYXRpb24gaGFzIGJlZW4gZXhhbWluZWQgYnV0IGhhcyBub3QgYmVlbiBmdWxs
eSB0ZXN0ZWQgZm9yIGNvbnNpc3RlbmN5Lg0KRm9yIHRoZSBUSUdFUi9MaW5lIFNoYXBlZmlsZXMs
IHRoZSBQb2ludCBhbmQgVmVjdG9yIE9iamVjdCBDb3VudCBmb3IgdGhlIEctcG9seWdvbiBTRFRT
IFBvaW50IGFuZCBWZWN0b3IgT2JqZWN0IFR5cGUgcmVmbGVjdHMgdGhlIG51bWJlciBvZiByZWNv
cmRzIGluIHRoZSBzaGFwZWZpbGUgYXR0cmlidXRlIHRhYmxlLiAgRm9yIG11bHRpLXBvbHlnb24g
ZmVhdHVyZXMsIG9ubHkgb25lIGF0dHJpYnV0ZSByZWNvcmQgZXhpc3RzIGZvciBlYWNoIG11bHRp
LXBvbHlnb24gcmF0aGVyIHRoYW4gb25lIGF0dHJpYnV0ZSByZWNvcmQgcGVyIGluZGl2aWR1YWwg
Ry1wb2x5Z29uIGNvbXBvbmVudCBvZiB0aGUgbXVsdGktcG9seWdvbiBmZWF0dXJlLiAgVElHRVIv
TGluZSBTaGFwZWZpbGUgbXVsdGktcG9seWdvbnMgYXJlIGFuIGV4Y2VwdGlvbiB0byB0aGUgRy1w
b2x5Z29uIG9iamVjdCB0eXBlIGNsYXNzaWZpY2F0aW9uLiAgVGhlcmVmb3JlLCB3aGVuIG11bHRp
LXBvbHlnb25zIGV4aXN0IGluIGEgc2hhcGVmaWxlLCB0aGUgb2JqZWN0IGNvdW50IHdpbGwgYmUg
bGVzcyB0aGFuIHRoZSBhY3R1YWwgbnVtYmVyIG9mIEctcG9seWdvbnMuPC9sb2dpYz4NCiAgICA8
Y29tcGxldGU+RGF0YSBjb21wbGV0ZW5lc3Mgb2YgdGhlIFRJR0VSL0xpbmUgU2hhcGVmaWxlcyBy
ZWZsZWN0cyB0aGUgY29udGVudHMgb2YgdGhlIENlbnN1cyBNQUYvVElHRVIgZGF0YWJhc2UgYXQg
dGhlIHRpbWUgdGhlIFRJR0VSL0xpbmUgU2hhcGVmaWxlcyB3ZXJlIGNyZWF0ZWQuPC9jb21wbGV0
ZT4NCiAgICA8bGluZWFnZT4NCiAgICAgIDxzcmNpbmZvPg0KICAgICAgICA8c3JjY2l0ZT4NCiAg
ICAgICAgICA8Y2l0ZWluZm8+DQogICAgICAgICAgICA8b3JpZ2luPlUuUy4gRGVwYXJ0bWVudCBv
ZiBDb21tZXJjZSwgVS5TLiBDZW5zdXMgQnVyZWF1LCBHZW9ncmFwaHkgRGl2aXNpb248L29yaWdp
bj4NCiAgICAgICAgICAgIDxwdWJkYXRlPlVucHVibGlzaGVkIG1hdGVyaWFsPC9wdWJkYXRlPg0K
ICAgICAgICAgICAgPHRpdGxlPkNlbnN1cyBNQUYvVElHRVIgZGF0YWJhc2U8L3RpdGxlPg0KICAg
ICAgICAgIDwvY2l0ZWluZm8+DQogICAgICAgIDwvc3JjY2l0ZT4NCiAgICAgICAgPHR5cGVzcmM+
b25saW5lPC90eXBlc3JjPg0KICAgICAgICA8c3JjdGltZT4NCiAgICAgICAgICA8dGltZWluZm8+
DQogICAgICAgICAgICA8cm5nZGF0ZXM+DQogICAgICAgICAgICAgIDxiZWdkYXRlPjIwMTAwMTwv
YmVnZGF0ZT4NCiAgICAgICAgICAgICAgPGVuZGRhdGU+MjAxMDA3PC9lbmRkYXRlPg0KICAgICAg
ICAgICAgPC9ybmdkYXRlcz4NCiAgICAgICAgICA8L3RpbWVpbmZvPg0KICAgICAgICAgIDxzcmNj
dXJyPlB1YmxpY2F0aW9uIERhdGU8L3NyY2N1cnI+DQogICAgICAgIDwvc3JjdGltZT4NCiAgICAg
ICAgPHNyY2NpdGVhPk1BRi9USUdFUjwvc3JjY2l0ZWE+DQogICAgICAgIDxzcmNjb250cj5UaGUg
c2VsZWN0ZWQgZ2VvZ3JhcGhpYyBhbmQgY2FydG9ncmFwaGljIGluZm9ybWF0aW9uIChsaW5lIHNl
Z21lbnRzKSBhcmUgZGVyaXZlZCBmcm9tIHRoZSBVLlMuIENlbnN1cyBCdXJlYXUncyBNYXN0ZXIg
QWRkcmVzcyBGaWxlIFRvcG9sb2dpY2FsbHkgSW50ZWdyYXRlZCBHZW9ncmFwaGljIEVuY29kaW5n
IGFuZCBSZWZlcmVuY2luZyAoTUFGL1RJR0VSKSBkYXRhYmFzZS48L3NyY2NvbnRyPg0KICAgICAg
PC9zcmNpbmZvPg0KICAgICAgPHByb2NzdGVwPg0KICAgICAgICA8cHJvY2Rlc2M+VElHRVIvTGlu
ZSBTaGFwZWZpbGVzIGFyZSBleHRyYWN0ZWQgZnJvbSB0aGUgQ2Vuc3VzIE1BRi9USUdFUiBkYXRh
YmFzZSBieSBuYXRpb24sIHN0YXRlLCBjb3VudHksIGFuZCBlbnRpdHkuICBDZW5zdXMgTUFGL1RJ
R0VSIGRhdGEgZm9yIGFsbCBvZiB0aGUgYWZvcmVtZW50aW9uZWQgZ2VvZ3JhcGhpYyBlbnRpdGll
cyBhcmUgdGhlbiBkaXN0cmlidXRlZCBhbW9uZyB0aGUgc2hhcGVmaWxlcyBlYWNoIGNvbnRhaW5p
bmcgYXR0cmlidXRlcyBmb3IgbGluZSwgcG9seWdvbiwgb3IgbGFuZG1hcmsgZ2VvZ3JhcGhpYyBk
YXRhLiA8L3Byb2NkZXNjPg0KICAgICAgICA8c3JjdXNlZD5DZW5zdXMgTUFGL1RJR0VSPC9zcmN1
c2VkPg0KICAgICAgICA8cHJvY2RhdGU+MjAxMDwvcHJvY2RhdGU+DQogICAgICA8L3Byb2NzdGVw
Pg0KICAgIDwvbGluZWFnZT4NCiAgPC9kYXRhcXVhbD4NCiAgPHNwZG9pbmZvPg0KICAgIDxpbmRz
cHJlZj5GZWRlcmFsIEluZm9ybWF0aW9uIFByb2Nlc3NpbmcgU3RhbmRhcmRzIChGSVBTKSwgQU5T
SSwgYW5kIGZlYXR1cmUgbmFtZXMuPC9pbmRzcHJlZj4NCiAgICA8ZGlyZWN0PlZlY3RvcjwvZGly
ZWN0Pg0KICA8L3NwZG9pbmZvPg0KICA8c3ByZWY+DQogICAgPGhvcml6c3lzPg0KICAgICAgPGdl
b2dyYXBoPg0KICAgICAgICA8bGF0cmVzPjAuMDAwNDU4PC9sYXRyZXM+DQogICAgICAgIDxsb25n
cmVzPjAuMDAwNDU4PC9sb25ncmVzPg0KICAgICAgICA8Z2VvZ3VuaXQ+RGVjaW1hbCBkZWdyZWVz
PC9nZW9ndW5pdD4NCiAgICAgIDwvZ2VvZ3JhcGg+DQogICAgICA8Z2VvZGV0aWM+DQogICAgICAg
IDxob3JpemRuPk5vcnRoIEFtZXJpY2FuIERhdHVtIG9mIDE5ODMgaW4gdGhlIDQ4IGNvbnRpZ3Vv
dXMgc3RhdGVzLCB0aGUgRGlzdHJpY3Qgb2YgQ29sdW1iaWEsIEFsYXNrYSwgSGF3YWlpLCBQdWVy
dG8gUmljbywgdGhlIFZpcmdpbiBJc2xhbmRzIG9mIHRoZSBVbml0ZWQgU3RhdGVzLCBhbmQgdGhl
IFBhY2lmaWMgSXNsYW5kIEFyZWFzLjwvaG9yaXpkbj4NCiAgICAgICAgPGVsbGlwcz5HZW9kZXRp
YyBSZWZlcmVuY2UgU3lzdGVtIDgwPC9lbGxpcHM+DQogICAgICAgIDxzZW1pYXhpcz42Mzc4MTM3
PC9zZW1pYXhpcz4NCiAgICAgICAgPGRlbmZsYXQ+Mjk4MjU3PC9kZW5mbGF0Pg0KICAgICAgPC9n
ZW9kZXRpYz4NCiAgICA8L2hvcml6c3lzPg0KICA8L3NwcmVmPg0KICA8ZWFpbmZvPg0KICAgIDxk
ZXRhaWxlZCBOYW1lPSJ0bF8yMDEwXzMxX3pjdGE1MTAiPg0KICAgICAgPGVudHR5cD4NCiAgICAg
ICAgPGVudHR5cGw+WkNUQTUxMC5zaHA8L2VudHR5cGw+DQogICAgICAgIDxlbnR0eXBkPjIwMTAg
Q2Vuc3VzIDUtZGlnaXQgWklQIENvZGUgVGFidWxhdGlvbiBBcmVhIChaQ1RBNSkgU3RhdGUtYmFz
ZWQ8L2VudHR5cGQ+DQogICAgICAgIDxlbnR0eXBkcz5VLlMuIENlbnN1cyBCdXJlYXU8L2VudHR5
cGRzPg0KICAgICAgICA8ZW50dHlwdCBTeW5jPSJUUlVFIj5GZWF0dXJlIENsYXNzPC9lbnR0eXB0
Pg0KICAgICAgICA8ZW50dHlwYyBTeW5jPSJUUlVFIj41ODY8L2VudHR5cGM+DQogICAgICA8L2Vu
dHR5cD4NCiAgICAgIDxhdHRyPg0KICAgICAgICA8YXR0cmxhYmwgU3luYz0iVFJVRSI+RklEPC9h
dHRybGFibD4NCiAgICAgICAgPGF0dGFsaWFzIFN5bmM9IlRSVUUiPkZJRDwvYXR0YWxpYXM+DQog
ICAgICAgIDxhdHRydHlwZSBTeW5jPSJUUlVFIj5PSUQ8L2F0dHJ0eXBlPg0KICAgICAgICA8YXR0
d2lkdGggU3luYz0iVFJVRSI+NDwvYXR0d2lkdGg+DQogICAgICAgIDxhdHByZWNpcyBTeW5jPSJU
UlVFIj4wPC9hdHByZWNpcz4NCiAgICAgICAgPGF0dHNjYWxlIFN5bmM9IlRSVUUiPjA8L2F0dHNj
YWxlPg0KICAgICAgICA8YXR0cmRlZiBTeW5jPSJUUlVFIj5JbnRlcm5hbCBmZWF0dXJlIG51bWJl
ci48L2F0dHJkZWY+DQogICAgICAgIDxhdHRyZGVmcyBTeW5jPSJUUlVFIj5FU1JJPC9hdHRyZGVm
cz4NCiAgICAgICAgPGF0dHJkb212Pg0KICAgICAgICAgIDx1ZG9tIFN5bmM9IlRSVUUiPlNlcXVl
bnRpYWwgdW5pcXVlIHdob2xlIG51bWJlcnMgdGhhdCBhcmUgYXV0b21hdGljYWxseSBnZW5lcmF0
ZWQuPC91ZG9tPg0KICAgICAgICA8L2F0dHJkb212Pg0KICAgICAgPC9hdHRyPg0KICAgICAgPGF0
dHI+DQogICAgICAgIDxhdHRybGFibCBTeW5jPSJUUlVFIj5TaGFwZTwvYXR0cmxhYmw+DQogICAg
ICAgIDxhdHRhbGlhcyBTeW5jPSJUUlVFIj5TaGFwZTwvYXR0YWxpYXM+DQogICAgICAgIDxhdHRy
dHlwZSBTeW5jPSJUUlVFIj5HZW9tZXRyeTwvYXR0cnR5cGU+DQogICAgICAgIDxhdHR3aWR0aCBT
eW5jPSJUUlVFIj4wPC9hdHR3aWR0aD4NCiAgICAgICAgPGF0cHJlY2lzIFN5bmM9IlRSVUUiPjA8
L2F0cHJlY2lzPg0KICAgICAgICA8YXR0c2NhbGUgU3luYz0iVFJVRSI+MDwvYXR0c2NhbGU+DQog
ICAgICAgIDxhdHRyZGVmIFN5bmM9IlRSVUUiPkZlYXR1cmUgZ2VvbWV0cnkuPC9hdHRyZGVmPg0K
ICAgICAgICA8YXR0cmRlZnMgU3luYz0iVFJVRSI+RVNSSTwvYXR0cmRlZnM+DQogICAgICAgIDxh
dHRyZG9tdj4NCiAgICAgICAgICA8dWRvbSBTeW5jPSJUUlVFIj5Db29yZGluYXRlcyBkZWZpbmlu
ZyB0aGUgZmVhdHVyZXMuPC91ZG9tPg0KICAgICAgICA8L2F0dHJkb212Pg0KICAgICAgPC9hdHRy
Pg0KICAgICAgPGF0dHI+DQogICAgICAgIDxhdHRybGFibD5TVEFURUZQMTA8L2F0dHJsYWJsPg0K
ICAgICAgICA8YXR0cmRlZj4yMDEwIENlbnN1cyBzdGF0ZSBGZWRlcmFsIEluZm9ybWF0aW9uIFBy
b2Nlc3NpbmcgU3RhbmRhcmRzDQogICAgICAgICAgICAgICAgIChGSVBTKSBjb2RlPC9hdHRyZGVm
Pg0KICAgICAgICA8YXR0cmRlZnM+VS5TLiBDZW5zdXMgQnVyZWF1PC9hdHRyZGVmcz4NCiAgICAg
ICAgPGF0dHJkb212Pg0KICAgICAgICAgIDxjb2Rlc2V0ZD4NCiAgICAgICAgICAgIDxjb2Rlc2V0
bj5JTkNJVFMuMzgtMjAweCAoUjIwMDQpLCBDb2RlcyBmb3IgdGhlIElkZW50aWZpY2F0aW9uIG9m
DQogICAgICAgICAgICAgICAgICAgICAgdGhlIFN0YXRlcywgdGhlIERpc3RyaWN0IG9mIENvbHVt
YmlhLCBQdWVydG8gUmljbywgYW5kIHRoZQ0KICAgICAgICAgICAgICAgICAgICAgIEluc3VsYXIg
QXJlYXMgb2YgdGhlIFVuaXRlZCBTdGF0ZXMgKEZvcm1lcmx5IEZJUFMgNS0yKTwvY29kZXNldG4+
DQogICAgICAgICAgICA8Y29kZXNldHM+VS5TLiBDZW5zdXMgQnVyZWF1PC9jb2Rlc2V0cz4NCiAg
ICAgICAgICA8L2NvZGVzZXRkPg0KICAgICAgICA8L2F0dHJkb212Pg0KICAgICAgICA8YXR0YWxp
YXMgU3luYz0iVFJVRSI+U1RBVEVGUDEwPC9hdHRhbGlhcz4NCiAgICAgICAgPGF0dHJ0eXBlIFN5
bmM9IlRSVUUiPlN0cmluZzwvYXR0cnR5cGU+DQogICAgICAgIDxhdHR3aWR0aCBTeW5jPSJUUlVF
Ij4yPC9hdHR3aWR0aD4NCiAgICAgICAgPGF0cHJlY2lzIFN5bmM9IlRSVUUiPjA8L2F0cHJlY2lz
Pg0KICAgICAgICA8YXR0c2NhbGUgU3luYz0iVFJVRSI+MDwvYXR0c2NhbGU+DQogICAgICA8L2F0
dHI+DQogICAgICA8YXR0cj4NCiAgICAgICAgPGF0dHJsYWJsPlpDVEE1Q0UxMDwvYXR0cmxhYmw+
DQogICAgICAgIDxhdHRyZGVmPjIwMTAgQ2Vuc3VzIDUtZGlnaXQgWklQIENvZGUgVGFidWxhdGlv
biBBcmVhIGNvZGU8L2F0dHJkZWY+DQogICAgICAgIDxhdHRyZGVmcz5VLlMuIENlbnN1cyBCdXJl
YXU8L2F0dHJkZWZzPg0KICAgICAgICA8YXR0cmRvbXY+DQogICAgICAgICAgPGVkb20+DQogICAg
ICAgICAgICA8ZWRvbXY+MDA0MDEgdG8gOTk5NTA8L2Vkb212Pg0KICAgICAgICAgICAgPGVkb212
ZD5GaXZlLWRpZ2l0IFpJUCBjb2RlPC9lZG9tdmQ+DQogICAgICAgICAgICA8ZWRvbXZkcz5VLlMu
IENlbnN1cyBCdXJlYXU8L2Vkb212ZHM+DQogICAgICAgICAgPC9lZG9tPg0KICAgICAgICA8L2F0
dHJkb212Pg0KICAgICAgICA8YXR0YWxpYXMgU3luYz0iVFJVRSI+WkNUQTVDRTEwPC9hdHRhbGlh
cz4NCiAgICAgICAgPGF0dHJ0eXBlIFN5bmM9IlRSVUUiPlN0cmluZzwvYXR0cnR5cGU+DQogICAg
ICAgIDxhdHR3aWR0aCBTeW5jPSJUUlVFIj41PC9hdHR3aWR0aD4NCiAgICAgICAgPGF0cHJlY2lz
IFN5bmM9IlRSVUUiPjA8L2F0cHJlY2lzPg0KICAgICAgICA8YXR0c2NhbGUgU3luYz0iVFJVRSI+
MDwvYXR0c2NhbGU+DQogICAgICA8L2F0dHI+DQogICAgICA8YXR0cj4NCiAgICAgICAgPGF0dHJs
YWJsPkdFT0lEMTA8L2F0dHJsYWJsPg0KICAgICAgICA8YXR0cmRlZj4yMDEwIENlbnN1cyA1LWRp
Z2l0IFpJUCBDb2RlIFRhYnVsYXRpb24gQXJlYSBpZGVudGlmaWVyLCAyMDEwDQogICAgICAgICAg
ICAgICAgIENlbnN1cyA1LWRpZ2l0IFpJUCBDb2RlIFRhYnVsYXRpb24gQXJlYSBjb2RlPC9hdHRy
ZGVmPg0KICAgICAgICA8YXR0cmRlZnM+VS5TLiBDZW5zdXMgQnVyZWF1PC9hdHRyZGVmcz4NCiAg
ICAgICAgPGF0dHJkb212Pg0KICAgICAgICAgIDx1ZG9tPjIwMTAgQ2Vuc3VzIDUtZGlnaXQgWklQ
IENvZGUgVGFidWxhdGlvbiBBcmVhIGNvZGUgZm91bmQgaW4NCiAgICAgICAgICAgICAgICBaQ1RB
NUNFMTA8L3Vkb20+DQogICAgICAgIDwvYXR0cmRvbXY+DQogICAgICAgIDxhdHRhbGlhcyBTeW5j
PSJUUlVFIj5HRU9JRDEwPC9hdHRhbGlhcz4NCiAgICAgICAgPGF0dHJ0eXBlIFN5bmM9IlRSVUUi
PlN0cmluZzwvYXR0cnR5cGU+DQogICAgICAgIDxhdHR3aWR0aCBTeW5jPSJUUlVFIj43PC9hdHR3
aWR0aD4NCiAgICAgICAgPGF0cHJlY2lzIFN5bmM9IlRSVUUiPjA8L2F0cHJlY2lzPg0KICAgICAg
ICA8YXR0c2NhbGUgU3luYz0iVFJVRSI+MDwvYXR0c2NhbGU+DQogICAgICA8L2F0dHI+DQogICAg
ICA8YXR0cj4NCiAgICAgICAgPGF0dHJsYWJsPkNMQVNTRlAxMDwvYXR0cmxhYmw+DQogICAgICAg
IDxhdHRyZGVmPjIwMTAgQ2Vuc3VzIEZlZGVyYWwgSW5mb3JtYXRpb24gUHJvY2Vzc2luZyBTdGFu
ZGFyZHMgKEZJUFMpIDU1DQogICAgICAgICAgICAgICAgIGNsYXNzIGNvZGU8L2F0dHJkZWY+DQog
ICAgICAgIDxhdHRyZGVmcz5VLlMuIENlbnN1cyBCdXJlYXU8L2F0dHJkZWZzPg0KICAgICAgICA8
YXR0cmRvbXY+DQogICAgICAgICAgPGVkb20+DQogICAgICAgICAgICA8ZWRvbXY+QjU8L2Vkb212
Pg0KICAgICAgICAgICAgPGVkb212ZD5GaXZlLWRpZ2l0IFpDVEE8L2Vkb212ZD4NCiAgICAgICAg
ICAgIDxlZG9tdmRzPlUuUy4gQ2Vuc3VzIEJ1cmVhdTwvZWRvbXZkcz4NCiAgICAgICAgICA8L2Vk
b20+DQogICAgICAgIDwvYXR0cmRvbXY+DQogICAgICAgIDxhdHRhbGlhcyBTeW5jPSJUUlVFIj5D
TEFTU0ZQMTA8L2F0dGFsaWFzPg0KICAgICAgICA8YXR0cnR5cGUgU3luYz0iVFJVRSI+U3RyaW5n
PC9hdHRydHlwZT4NCiAgICAgICAgPGF0dHdpZHRoIFN5bmM9IlRSVUUiPjI8L2F0dHdpZHRoPg0K
ICAgICAgICA8YXRwcmVjaXMgU3luYz0iVFJVRSI+MDwvYXRwcmVjaXM+DQogICAgICAgIDxhdHRz
Y2FsZSBTeW5jPSJUUlVFIj4wPC9hdHRzY2FsZT4NCiAgICAgIDwvYXR0cj4NCiAgICAgIDxhdHRy
Pg0KICAgICAgICA8YXR0cmxhYmw+TVRGQ0MxMDwvYXR0cmxhYmw+DQogICAgICAgIDxhdHRyZGVm
Pk1BRi9USUdFUiBmZWF0dXJlIGNsYXNzIGNvZGU8L2F0dHJkZWY+DQogICAgICAgIDxhdHRyZGVm
cz5VLlMuIENlbnN1cyBCdXJlYXU8L2F0dHJkZWZzPg0KICAgICAgICA8YXR0cmRvbXY+DQogICAg
ICAgICAgPGVkb20+DQogICAgICAgICAgICA8ZWRvbXY+RzYzNTA8L2Vkb212Pg0KICAgICAgICAg
ICAgPGVkb212ZD5aSVAgQ29kZSBUYWJ1bGF0aW9uIEFyZWEgKDUtZGlnaXQpPC9lZG9tdmQ+DQog
ICAgICAgICAgICA8ZWRvbXZkcz5VLlMuIENlbnN1cyBCdXJlYXU8L2Vkb212ZHM+DQogICAgICAg
ICAgPC9lZG9tPg0KICAgICAgICA8L2F0dHJkb212Pg0KICAgICAgICA8YXR0YWxpYXMgU3luYz0i
VFJVRSI+TVRGQ0MxMDwvYXR0YWxpYXM+DQogICAgICAgIDxhdHRydHlwZSBTeW5jPSJUUlVFIj5T
dHJpbmc8L2F0dHJ0eXBlPg0KICAgICAgICA8YXR0d2lkdGggU3luYz0iVFJVRSI+NTwvYXR0d2lk
dGg+DQogICAgICAgIDxhdHByZWNpcyBTeW5jPSJUUlVFIj4wPC9hdHByZWNpcz4NCiAgICAgICAg
PGF0dHNjYWxlIFN5bmM9IlRSVUUiPjA8L2F0dHNjYWxlPg0KICAgICAgPC9hdHRyPg0KICAgICAg
PGF0dHI+DQogICAgICAgIDxhdHRybGFibD5GVU5DU1RBVDEwPC9hdHRybGFibD4NCiAgICAgICAg
PGF0dHJkZWY+MjAxMCBDZW5zdXMgZnVuY3Rpb25hbCBzdGF0dXM8L2F0dHJkZWY+DQogICAgICAg
IDxhdHRyZGVmcz5VLlMuIENlbnN1cyBCdXJlYXU8L2F0dHJkZWZzPg0KICAgICAgICA8YXR0cmRv
bXY+DQogICAgICAgICAgPGVkb20+DQogICAgICAgICAgICA8ZWRvbXY+UzwvZWRvbXY+DQogICAg
ICAgICAgICA8ZWRvbXZkPlN0YXRpc3RpY2FsIGVudGl0eTwvZWRvbXZkPg0KICAgICAgICAgICAg
PGVkb212ZHM+VS5TLiBDZW5zdXMgQnVyZWF1PC9lZG9tdmRzPg0KICAgICAgICAgIDwvZWRvbT4N
CiAgICAgICAgPC9hdHRyZG9tdj4NCiAgICAgICAgPGF0dGFsaWFzIFN5bmM9IlRSVUUiPkZVTkNT
VEFUMTA8L2F0dGFsaWFzPg0KICAgICAgICA8YXR0cnR5cGUgU3luYz0iVFJVRSI+U3RyaW5nPC9h
dHRydHlwZT4NCiAgICAgICAgPGF0dHdpZHRoIFN5bmM9IlRSVUUiPjE8L2F0dHdpZHRoPg0KICAg
ICAgICA8YXRwcmVjaXMgU3luYz0iVFJVRSI+MDwvYXRwcmVjaXM+DQogICAgICAgIDxhdHRzY2Fs
ZSBTeW5jPSJUUlVFIj4wPC9hdHRzY2FsZT4NCiAgICAgIDwvYXR0cj4NCiAgICAgIDxhdHRyPg0K
ICAgICAgICA8YXR0cmxhYmw+QUxBTkQxMDwvYXR0cmxhYmw+DQogICAgICAgIDxhdHRyZGVmPjIw
MTAgQ2Vuc3VzIGxhbmQgYXJlYSAoc3F1YXJlIG1ldGVycyk8L2F0dHJkZWY+DQogICAgICAgIDxh
dHRyZGVmcz5VLlMuIENlbnN1cyBCdXJlYXU8L2F0dHJkZWZzPg0KICAgICAgICA8YXR0cmRvbXY+
DQogICAgICAgICAgPGVkb20+DQogICAgICAgICAgICA8ZWRvbXY+MCB0byA5LDk5OSw5OTksOTk5
LDk5OTwvZWRvbXY+DQogICAgICAgICAgICA8ZWRvbXZkPkJsYW5rPC9lZG9tdmQ+DQogICAgICAg
ICAgICA8ZWRvbXZkcz5VLlMuIENlbnN1cyBCdXJlYXU8L2Vkb212ZHM+DQogICAgICAgICAgPC9l
ZG9tPg0KICAgICAgICA8L2F0dHJkb212Pg0KICAgICAgICA8YXR0YWxpYXMgU3luYz0iVFJVRSI+
QUxBTkQxMDwvYXR0YWxpYXM+DQogICAgICAgIDxhdHRydHlwZSBTeW5jPSJUUlVFIj5Eb3VibGU8
L2F0dHJ0eXBlPg0KICAgICAgICA8YXR0d2lkdGggU3luYz0iVFJVRSI+MTQ8L2F0dHdpZHRoPg0K
ICAgICAgICA8YXRwcmVjaXMgU3luYz0iVFJVRSI+MTQ8L2F0cHJlY2lzPg0KICAgICAgICA8YXR0
c2NhbGUgU3luYz0iVFJVRSI+MDwvYXR0c2NhbGU+DQogICAgICA8L2F0dHI+DQogICAgICA8YXR0
cj4NCiAgICAgICAgPGF0dHJsYWJsPkFXQVRFUjEwPC9hdHRybGFibD4NCiAgICAgICAgPGF0dHJk
ZWY+MjAxMCBDZW5zdXMgd2F0ZXIgYXJlYSAoc3F1YXJlIG1ldGVycyk8L2F0dHJkZWY+DQogICAg
ICAgIDxhdHRyZGVmcz5VLlMuIENlbnN1cyBCdXJlYXU8L2F0dHJkZWZzPg0KICAgICAgICA8YXR0
cmRvbXY+DQogICAgICAgICAgPGVkb20+DQogICAgICAgICAgICA8ZWRvbXY+MCB0byA5LDk5OSw5
OTksOTk5LDk5OTwvZWRvbXY+DQogICAgICAgICAgICA8ZWRvbXZkPkJsYW5rPC9lZG9tdmQ+DQog
ICAgICAgICAgICA8ZWRvbXZkcz5VLlMuIENlbnN1cyBCdXJlYXU8L2Vkb212ZHM+DQogICAgICAg
ICAgPC9lZG9tPg0KICAgICAgICA8L2F0dHJkb212Pg0KICAgICAgICA8YXR0YWxpYXMgU3luYz0i
VFJVRSI+QVdBVEVSMTA8L2F0dGFsaWFzPg0KICAgICAgICA8YXR0cnR5cGUgU3luYz0iVFJVRSI+
RG91YmxlPC9hdHRydHlwZT4NCiAgICAgICAgPGF0dHdpZHRoIFN5bmM9IlRSVUUiPjE0PC9hdHR3
aWR0aD4NCiAgICAgICAgPGF0cHJlY2lzIFN5bmM9IlRSVUUiPjE0PC9hdHByZWNpcz4NCiAgICAg
ICAgPGF0dHNjYWxlIFN5bmM9IlRSVUUiPjA8L2F0dHNjYWxlPg0KICAgICAgPC9hdHRyPg0KICAg
ICAgPGF0dHI+DQogICAgICAgIDxhdHRybGFibD5JTlRQVExBVDEwPC9hdHRybGFibD4NCiAgICAg
ICAgPGF0dHJkZWY+MjAxMCBDZW5zdXMgbGF0aXR1ZGUgb2YgdGhlIGludGVybmFsIHBvaW50PC9h
dHRyZGVmPg0KICAgICAgICA8YXR0cmRlZnM+VS5TLiBDZW5zdXMgQnVyZWF1PC9hdHRyZGVmcz4N
CiAgICAgICAgPGF0dHJkb212Pg0KICAgICAgICAgIDxlZG9tPg0KICAgICAgICAgICAgPGVkb212
PjAwPC9lZG9tdj4NCiAgICAgICAgICAgIDxlZG9tdmQ+Qmxhbms8L2Vkb212ZD4NCiAgICAgICAg
ICAgIDxlZG9tdmRzPlUuUy4gQ2Vuc3VzIEJ1cmVhdTwvZWRvbXZkcz4NCiAgICAgICAgICA8L2Vk
b20+DQogICAgICAgIDwvYXR0cmRvbXY+DQogICAgICAgIDxhdHRhbGlhcyBTeW5jPSJUUlVFIj5J
TlRQVExBVDEwPC9hdHRhbGlhcz4NCiAgICAgICAgPGF0dHJ0eXBlIFN5bmM9IlRSVUUiPlN0cmlu
ZzwvYXR0cnR5cGU+DQogICAgICAgIDxhdHR3aWR0aCBTeW5jPSJUUlVFIj4xMTwvYXR0d2lkdGg+
DQogICAgICAgIDxhdHByZWNpcyBTeW5jPSJUUlVFIj4wPC9hdHByZWNpcz4NCiAgICAgICAgPGF0
dHNjYWxlIFN5bmM9IlRSVUUiPjA8L2F0dHNjYWxlPg0KICAgICAgPC9hdHRyPg0KICAgICAgPGF0
dHI+DQogICAgICAgIDxhdHRybGFibD5JTlRQVExPTjEwPC9hdHRybGFibD4NCiAgICAgICAgPGF0
dHJkZWY+MjAxMCBDZW5zdXMgbG9uZ2l0dWRlIG9mIHRoZSBpbnRlcm5hbCBwb2ludDwvYXR0cmRl
Zj4NCiAgICAgICAgPGF0dHJkZWZzPlUuUy4gQ2Vuc3VzIEJ1cmVhdTwvYXR0cmRlZnM+DQogICAg
ICAgIDxhdHRyZG9tdj4NCiAgICAgICAgICA8ZWRvbT4NCiAgICAgICAgICAgIDxlZG9tdj4wMDwv
ZWRvbXY+DQogICAgICAgICAgICA8ZWRvbXZkPkJsYW5rPC9lZG9tdmQ+DQogICAgICAgICAgICA8
ZWRvbXZkcz5VLlMuIENlbnN1cyBCdXJlYXU8L2Vkb212ZHM+DQogICAgICAgICAgPC9lZG9tPg0K
ICAgICAgICA8L2F0dHJkb212Pg0KICAgICAgICA8YXR0YWxpYXMgU3luYz0iVFJVRSI+SU5UUFRM
T04xMDwvYXR0YWxpYXM+DQogICAgICAgIDxhdHRydHlwZSBTeW5jPSJUUlVFIj5TdHJpbmc8L2F0
dHJ0eXBlPg0KICAgICAgICA8YXR0d2lkdGggU3luYz0iVFJVRSI+MTI8L2F0dHdpZHRoPg0KICAg
ICAgICA8YXRwcmVjaXMgU3luYz0iVFJVRSI+MDwvYXRwcmVjaXM+DQogICAgICAgIDxhdHRzY2Fs
ZSBTeW5jPSJUUlVFIj4wPC9hdHRzY2FsZT4NCiAgICAgIDwvYXR0cj4NCiAgICAgIDxhdHRyPg0K
ICAgICAgICA8YXR0cmxhYmw+UEFSVEZMRzEwPC9hdHRybGFibD4NCiAgICAgICAgPGF0dHJkZWY+
UGFydCBmbGFnIGlkZW50aWZ5aW5nIGlmIGFsbCBvciBwYXJ0IG9mIHRoZSAyMDEwIENlbnN1cyBl
bnRpdHkNCiAgICAgICAgICAgICAgICAgaXMgd2l0aGluIHRoZSBmaWxlPC9hdHRyZGVmPg0KICAg
ICAgICA8YXR0cmRlZnM+VS5TLiBDZW5zdXMgQnVyZWF1PC9hdHRyZGVmcz4NCiAgICAgICAgPGF0
dHJkb212Pg0KICAgICAgICAgIDxlZG9tPg0KICAgICAgICAgICAgPGVkb212PjAwPC9lZG9tdj4N
CiAgICAgICAgICAgIDxlZG9tdmQ+Qmxhbms8L2Vkb212ZD4NCiAgICAgICAgICAgIDxlZG9tdmRz
PlUuUy4gQ2Vuc3VzIEJ1cmVhdTwvZWRvbXZkcz4NCiAgICAgICAgICA8L2Vkb20+DQogICAgICAg
IDwvYXR0cmRvbXY+DQogICAgICAgIDxhdHRhbGlhcyBTeW5jPSJUUlVFIj5QQVJURkxHMTA8L2F0
dGFsaWFzPg0KICAgICAgICA8YXR0cnR5cGUgU3luYz0iVFJVRSI+U3RyaW5nPC9hdHRydHlwZT4N
CiAgICAgICAgPGF0dHdpZHRoIFN5bmM9IlRSVUUiPjE8L2F0dHdpZHRoPg0KICAgICAgICA8YXRw
cmVjaXMgU3luYz0iVFJVRSI+MDwvYXRwcmVjaXM+DQogICAgICAgIDxhdHRzY2FsZSBTeW5jPSJU
UlVFIj4wPC9hdHRzY2FsZT4NCiAgICAgIDwvYXR0cj4NCiAgICA8L2RldGFpbGVkPg0KICA8L2Vh
aW5mbz4NCiAgPGRpc3RpbmZvPg0KICAgIDxkaXN0cmliPg0KICAgICAgPGNudGluZm8+DQogICAg
ICAgIDxjbnRvcmdwPg0KICAgICAgICAgIDxjbnRvcmc+VS5TLiBEZXBhcnRtZW50IG9mIENvbW1l
cmNlLCBVLlMuIENlbnN1cyBCdXJlYXUsIEdlb2dyYXBoeSBEaXZpc2lvbiwgR2VvZ3JhcGhpYyBQ
cm9kdWN0cyBCcmFuY2g8L2NudG9yZz4NCiAgICAgICAgPC9jbnRvcmdwPg0KICAgICAgICA8Y250
YWRkcj4NCiAgICAgICAgICA8YWRkcnR5cGU+TWFpbGluZyBhZGRyZXNzPC9hZGRydHlwZT4NCiAg
ICAgICAgICA8YWRkcmVzcz40NjAwIFNpbHZlciBIaWxsIFJvYWQsIFN0b3AgNzQwMDwvYWRkcmVz
cz4NCiAgICAgICAgICA8Y2l0eT5XYXNoaW5ndG9uPC9jaXR5Pg0KICAgICAgICAgIDxzdGF0ZT5E
Qzwvc3RhdGU+DQogICAgICAgICAgPHBvc3RhbD4yMDIzMy03NDAwPC9wb3N0YWw+DQogICAgICAg
ICAgPGNvdW50cnk+VW5pdGVkIFN0YXRlczwvY291bnRyeT4NCiAgICAgICAgPC9jbnRhZGRyPg0K
ICAgICAgICA8Y250dm9pY2U+MzAxLTc2My0xMTI4PC9jbnR2b2ljZT4NCiAgICAgICAgPGNudGZh
eD4zMDEtNzYzLTQ3MTA8L2NudGZheD4NCiAgICAgICAgPGNudGVtYWlsPmdlby50aWdlckBjZW5z
dXMuZ292PC9jbnRlbWFpbD4NCiAgICAgIDwvY250aW5mbz4NCiAgICA8L2Rpc3RyaWI+DQogICAg
PGRpc3RsaWFiPk5vIHdhcnJhbnR5LCBleHByZXNzZWQgb3IgaW1wbGllZCBpcyBtYWRlIHdpdGgg
cmVnYXJkIHRvIHRoZSBhY2N1cmFjeSBvZiB0aGVzZSBkYXRhLCBhbmQgbm8gbGlhYmlsaXR5IGlz
IGFzc3VtZWQgYnkgdGhlIFUuUy4gR292ZXJubWVudCBpbiBnZW5lcmFsIG9yIHRoZSBVLlMuIENl
bnN1cyBCdXJlYXUgaW4gc3BlY2lmaWMgYXMgdG8gdGhlIHNwYXRpYWwgb3IgYXR0cmlidXRlIGFj
Y3VyYWN5IG9mIHRoZSBkYXRhLiAgVGhlIGFjdCBvZiBkaXN0cmlidXRpb24gc2hhbGwgbm90IGNv
bnN0aXR1dGUgYW55IHN1Y2ggd2FycmFudHkgYW5kIG5vIHJlc3BvbnNpYmlsaXR5IGlzIGFzc3Vt
ZWQgYnkgdGhlIFUuUy4gZ292ZXJubWVudCBpbiB0aGUgdXNlIG9mIHRoZXNlIGZpbGVzLiAgVGhl
IGJvdW5kYXJ5IGluZm9ybWF0aW9uIGluIHRoZSBUSUdFUi9MaW5lIFNoYXBlZmlsZXMgaXMgZm9y
IHN0YXRpc3RpY2FsIGRhdGEgY29sbGVjdGlvbiBhbmQgdGFidWxhdGlvbiBwdXJwb3NlcyBvbmx5
OyB0aGVpciBkZXBpY3Rpb24gYW5kIGRlc2lnbmF0aW9uIGZvciBzdGF0aXN0aWNhbCBwdXJwb3Nl
cyBkbyBub3QgY29uc3RpdHV0ZSBhIGRldGVybWluYXRpb24gb2YganVyaXNkaWN0aW9uYWwgYXV0
aG9yaXR5IG9yIHJpZ2h0cyBvZiBvd25lcnNoaXAgb3IgZW50aXRsZW1lbnQgYW5kIHRoZXkgYXJl
IG5vdCBsZWdhbCBsYW5kIGRlc2NyaXB0aW9ucy48L2Rpc3RsaWFiPg0KICAgIDxzdGRvcmRlcj4N
CiAgICAgIDxkaWdmb3JtPg0KICAgICAgICA8ZGlndGluZm8+DQogICAgICAgICAgPGZvcm1uYW1l
PlRHUlNIUCAoY29tcHJlc3NlZCk8L2Zvcm1uYW1lPg0KICAgICAgICAgIDxmaWxlZGVjPlBLLVpJ
UCwgdmVyc2lvbiAxLjkzIEEgb3IgaGlnaGVyPC9maWxlZGVjPg0KICAgICAgICA8L2RpZ3RpbmZv
Pg0KICAgICAgICA8ZGlndG9wdD4NCiAgICAgICAgICA8b25saW5vcHQ+DQogICAgICAgICAgICA8
Y29tcHV0ZXI+DQogICAgICAgICAgICAgIDxuZXR3b3JrYT4NCiAgICAgICAgICAgICAgICA8bmV0
d29ya3I+aHR0cDovL3d3dy5jZW5zdXMuZ292L2dlby93d3cvdGlnZXI8L25ldHdvcmtyPg0KICAg
ICAgICAgICAgICA8L25ldHdvcmthPg0KICAgICAgICAgICAgPC9jb21wdXRlcj4NCiAgICAgICAg
ICA8L29ubGlub3B0Pg0KICAgICAgICAgIDxvZmZvcHRuPg0KICAgICAgICAgICAgPG9mZm1lZGlh
PkRWRC1ST00gKE9ubHkgaWYgb2ZmZXJlZCBvZmZsaW5lKTwvb2ZmbWVkaWE+DQogICAgICAgICAg
ICA8cmVjZm10PklTTyA5NjYwPC9yZWNmbXQ+DQogICAgICAgICAgPC9vZmZvcHRuPg0KICAgICAg
ICA8L2RpZ3RvcHQ+DQogICAgICA8L2RpZ2Zvcm0+DQogICAgICA8ZmVlcz5UaGUgb25saW5lIGNv
cHkgb2YgdGhlIFRJR0VSL0xpbmUgZmlsZXMgbWF5IGJlIGFjY2Vzc2VkIHdpdGhvdXQgY2hhcmdl
LjwvZmVlcz4NCiAgICAgIDxvcmRlcmluZz5UbyBvYnRhaW4gbW9yZSBpbmZvcm1hdGlvbiBhYm91
dCBvcmRlcmluZyBUSUdFUi9MaW5lIHNoYXBlZmlsZXMgdmlzaXQgaHR0cDovL3d3dy5jZW5zdXMu
Z292L2dlby93d3cvdGlnZXIgPC9vcmRlcmluZz4NCiAgICA8L3N0ZG9yZGVyPg0KICAgIDx0ZWNo
cHJlcT5UaGUgVElHRVIvTGluZSBzaGFwZWZpbGVzIGNvbnRhaW4gZ2VvZ3JhcGhpYyBkYXRhIG9u
bHkgYW5kIGRvIG5vdCBpbmNsdWRlIGRpc3BsYXkgbWFwcGluZyBzb2Z0d2FyZSBvciBzdGF0aXN0
aWNhbCBkYXRhLiAgRm9yIGluZm9ybWF0aW9uIG9uIGhvdyB0byB1c2UgdGhlIFRJR0VSL0xpbmUg
c2hhcGVmaWxlIGRhdGEgd2l0aCBzcGVjaWZpYyBzb2Z0d2FyZSBwYWNrYWdlIHVzZXJzIHNoYWxs
IGNvbnRhY3QgdGhlIGNvbXBhbnkgdGhhdCBwcm9kdWNlZCB0aGUgc29mdHdhcmUuPC90ZWNocHJl
cT4NCiAgPC9kaXN0aW5mbz4NCiAgPG1ldGFpbmZvPg0KICAgIDxtZXRkPjIwMTAwNTA3PC9tZXRk
Pg0KICAgIDxtZXRjPg0KICAgICAgPGNudGluZm8+DQogICAgICAgIDxjbnRvcmdwPg0KICAgICAg
ICAgIDxjbnRvcmc+VS5TLiBEZXBhcnRtZW50IG9mIENvbW1lcmNlLCBVLlMuIENlbnN1cyBCdXJl
YXUsIEdlb2dyYXBoeSBEaXZpc2lvbiwgR2VvZ3JhcGhpYyBQcm9kdWN0cyBCcmFuY2g8L2NudG9y
Zz4NCiAgICAgICAgPC9jbnRvcmdwPg0KICAgICAgICA8Y250YWRkcj4NCiAgICAgICAgICA8YWRk
cnR5cGU+TWFpbGluZyBhZGRyZXNzPC9hZGRydHlwZT4NCiAgICAgICAgICA8YWRkcmVzcz40NjAw
IFNpbHZlciBIaWxsIFJvYWQsIFN0b3AgNzQwMDwvYWRkcmVzcz4NCiAgICAgICAgICA8Y2l0eT5X
YXNoaW5ndG9uPC9jaXR5Pg0KICAgICAgICAgIDxzdGF0ZT5EQzwvc3RhdGU+DQogICAgICAgICAg
PHBvc3RhbD4yMDIzMy03NDAwPC9wb3N0YWw+DQogICAgICAgICAgPGNvdW50cnk+VW5pdGVkIFN0
YXRlczwvY291bnRyeT4NCiAgICAgICAgPC9jbnRhZGRyPg0KICAgICAgICA8Y250dm9pY2U+MzAx
LTc2My0xMTI4PC9jbnR2b2ljZT4NCiAgICAgICAgPGNudGZheD4zMDEtNzYzLTQ3MTA8L2NudGZh
eD4NCiAgICAgICAgPGNudGVtYWlsPmdlby50aWdlckBjZW5zdXMuZ292PC9jbnRlbWFpbD4NCiAg
ICAgIDwvY250aW5mbz4NCiAgICA8L21ldGM+DQogICAgPG1ldHN0ZG4+RkdEQyBDb250ZW50IFN0
YW5kYXJkcyBmb3IgRGlnaXRhbCBHZW9zcGF0aWFsIE1ldGFkYXRhPC9tZXRzdGRuPg0KICAgIDxt
ZXRzdGR2PkZHREMtU1RELTAwMS0xOTk4PC9tZXRzdGR2Pg0KICAgIDxNZXRhZGF0YV9DaGFyYWN0
ZXJfU2V0Pjg4NTlwYXJ0MTwvTWV0YWRhdGFfQ2hhcmFjdGVyX1NldD4NCiAgICA8TWV0YWRhdGFf
RmlsZV9JZGVudGlmaWVyPnRsXzIwMTBfMzFfemN0YTUxMC5zaHAueG1sPC9NZXRhZGF0YV9GaWxl
X0lkZW50aWZpZXI+DQogICAgPE1ldGFkYXRhX0xhbmd1YWdlPmVuZzwvTWV0YWRhdGFfTGFuZ3Vh
Z2U+DQogIDwvbWV0YWluZm8+DQogIDxFc3JpPg0KICAgIDxTeW5jRGF0ZT4yMDEyMDMxOTwvU3lu
Y0RhdGU+DQogICAgPFN5bmNUaW1lPjEwMTcwNjAwPC9TeW5jVGltZT4NCiAgICA8TW9kRGF0ZT4y
MDEyMDMxOTwvTW9kRGF0ZT4NCiAgICA8TW9kVGltZT4xMDE3MDYwMDwvTW9kVGltZT4NCiAgPC9F
c3JpPg0KPC9tZXRhZGF0YT4=</Data></Enclosure></Binary><mdHrLvName Sync="TRUE">dataset</mdHrLvName><refSysInfo><RefSystem><refSysID><identCode code="4269" Sync="TRUE" value="26852"/><idCodeSpace Sync="TRUE">EPSG</idCodeSpace><idVersion Sync="TRUE">7.4.1</idVersion></refSysID></RefSystem></refSysInfo></metadata>
